{
  "Frequency": 146.8,
  "Offset": -0.6,
  "Tone": 88.5,
  "Call": "AE7TA",
  "Location": "Grace, Sedgwick Peak",
  "ST/PR": "ID",
  "Use": "OPEN",
  "VOIP": "",
  "DGTL": "",
  "Mi": 155.41,
  "Dir": "NE",
  "": "",
  "state_id": "16",
  "ID": "128",
  "Latitude": 42.51589966,
  "Longitude": -111.92299652,
  "Downlink": 146.8,
  "Uplink": 146.2,
  "Uplink Tone": 88.5,
  "County": "Bannock",
  "Grid": "DN42AM",
  "Op Status": "On-Air",
  "Coverage": "Wide area. Idaho Falls, ID to Brigham City, UT.",
  "Sponsor": "Sedgwick Peak ARC",
  "Features": 9,
  "FM": "Yes; analog capable.",
  "Analog Bandwidth": "",
  "Nets": "SPARC: 1st Wed at 20:00.",
  "Coordination": "UVHFS",
  "Last update": "2016-12-13"
}