{
  "Frequency": 147.2,
  "Offset": 0.6,
  "Tone": "",
  "Call": "K7WIR",
  "Location": "Jerome",
  "ST/PR": "ID",
  "Use": "OPEN",
  "Mode": "Fusion",
  "Mi": 138.75,
  "Dir": "NNW",
  "": "",
  "state_id": "16",
  "ID": "19288",
  "Latitude": 42.7199873,
  "Longitude": -114.5240341,
  "Downlink": 147.2,
  "Uplink": 147.8,
  "YSF Digital Enabled": true,
  "DG-ID": "Open ↑ / Open ↓",
  "County": "Jerome",
  "Op Status": "On-Air",
  "Coverage": "Local area linked repeater near Jerome Idaho",
  "Sponsor": "kd7lxw",
  "Affiliate": "K7WIR",
  "Features": "C4FM linked system",
  "Links": "Full-time to 443.35000 (K7WIR) at Idaho City, Grimes Creek, ID .",
  "Notes": "K7WIR Linked system",
  "Last update": "2020-11-03"
}