{
  "Frequency": 224.24,
  "Offset": -1.6,
  "Tone": 156.7,
  "Call": "KF7X",
  "Location": "Lake Havasu City",
  "ST/PR": "AZ",
  "Use": "OPEN",
  "Mode": "FM",
  "Mi": 125.05,
  "Dir": "SSE",
  "": "",
  "state_id": "04",
  "ID": "193",
  "Latitude": 34.49089813,
  "Longitude": -114.31199646,
  "Downlink": 224.24,
  "Uplink": 222.64,
  "Uplink Tone": 156.7,
  "County": "Mohave",
  "Grid": "DM24UL",
  "Op Status": "On-Air",
  "Sponsor": "KF7X",
  "Features": "Closed autopatch.",
  "FM": "Yes; analog capable.",
  "Analog Bandwidth": "",
  "Coordination": "ARCA",
  "Last update": "2019-04-15"
}