{
  "Frequency": 146.64,
  "Offset": -0.6,
  "Tone": 156.7,
  "Call": "K7LHC",
  "Location": "Lake Havasu City",
  "ST/PR": "AZ",
  "Use": "OPEN",
  "Mode": "FM Fusion",
  "Mi": 125.29,
  "Dir": "SSE",
  "": "",
  "state_id": "04",
  "ID": "45",
  "Latitude": 34.48389816,
  "Longitude": -114.3219986,
  "Downlink": 146.64,
  "Uplink": 146.04,
  "Uplink Tone": 156.7,
  "YSF Digital Enabled": true,
  "DG-ID": "Open ↑ / Open ↓",
  "County": "Mohave",
  "Op Status": "On-Air",
  "Coverage": 30,
  "Sponsor": "London Bridge Amateur Radio Association, Inc K7LHC",
  "Features": "E-power.",
  "FM": "Yes; analog capable.",
  "Analog Bandwidth": "",
  "Web links": "London Bridge Amateur Radio Association, Inc K7LHC",
  "Coordination": "ARCA",
  "Last update": "2019-05-05"
}