[
  {
    "Location": 0,
    "Name": "KEGcentennial",
    "Frequency": 147.315,
    "Duplex": "+",
    "Offset": 0.6,
    "Tone": "",
    "rToneFreq": 88.5,
    "cToneFreq": 88.5,
    "DtcsCode": 23,
    "DtcsRxCode": 23,
    "DtcsPolarity": "NN",
    "Mode": "DV",
    "TStep": 5,
    "Comment": "CO Arapahoe Centennial N0KEG N0KEG Parker Radio Association 147.315 OPEN "
  },
  {
    "Location": 1,
    "Name": "KEGparker",
    "Frequency": 448.05,
    "Duplex": "-",
    "Offset": 5,
    "Tone": "",
    "rToneFreq": 88.5,
    "cToneFreq": 88.5,
    "DtcsCode": 23,
    "DtcsRxCode": 23,
    "DtcsPolarity": "NN",
    "Mode": "DMR",
    "TStep": 5,
    "Comment": "CO Douglas Parker N0KEG 448.05 OPEN "
  },
  {
    "Location": 2,
    "Name": "AENaurora",
    "Frequency": 449.15,
    "Duplex": "-",
    "Offset": 5,
    "Tone": "Tone",
    "rToneFreq": 136.5,
    "cToneFreq": 136.5,
    "DtcsCode": 23,
    "DtcsRxCode": 23,
    "DtcsPolarity": "NN",
    "Mode": "DV",
    "TStep": 5,
    "Comment": "CO Arapahoe Aurora WR0AEN Colorado Amateur Repeater Network (CARN) 449.15 OPEN On-Air"
  },
  {
    "Location": 3,
    "Name": "AENdenver",
    "Frequency": 449.65,
    "Duplex": "-",
    "Offset": 5,
    "Tone": "Tone",
    "rToneFreq": 136.5,
    "cToneFreq": 136.5,
    "DtcsCode": 23,
    "DtcsRxCode": 23,
    "DtcsPolarity": "NN",
    "Mode": "DV",
    "TStep": 5,
    "Comment": "CO Denver Denver WR0AEN Colorado Amateur Repeater Network (CARN) 449.65 OPEN On-Air"
  },
  {
    "Location": 4,
    "Name": "AENdenver",
    "Frequency": 449.675,
    "Duplex": "-",
    "Offset": 5,
    "Tone": "Tone",
    "rToneFreq": 136.5,
    "cToneFreq": 136.5,
    "DtcsCode": 23,
    "DtcsRxCode": 23,
    "DtcsPolarity": "NN",
    "Mode": "DV",
    "TStep": 5,
    "Comment": "CO Denver Denver WR0AEN Colorado Amateur Repeater Network (CARN) 449.675 OPEN On-Air"
  },
  {
    "Location": 5,
    "Name": "AENidahosprings,squawmountain",
    "Frequency": 449,
    "Duplex": "-",
    "Offset": 5,
    "Tone": "Tone",
    "rToneFreq": 136.5,
    "cToneFreq": 136.5,
    "DtcsCode": 23,
    "DtcsRxCode": 23,
    "DtcsPolarity": "NN",
    "Mode": "FM",
    "TStep": 5,
    "Comment": "CO Clear Creek Idaho Springs, Squaw Mountain WR0AEN CARN 449 OPEN On-Air"
  },
  {
    "Location": 6,
    "Name": "AENgreeley",
    "Frequency": 449.325,
    "Duplex": "-",
    "Offset": 5,
    "Tone": "Tone",
    "rToneFreq": 136.5,
    "cToneFreq": 136.5,
    "DtcsCode": 23,
    "DtcsRxCode": 23,
    "DtcsPolarity": "NN",
    "Mode": "DV",
    "TStep": 5,
    "Comment": "CO Weld Greeley WR0AEN Colorado Amateur Repeater Network (CARN) 449.325 OPEN On-Air"
  },
  {
    "Location": 7,
    "Name": "ZUQaurora",
    "Frequency": 448.4,
    "Duplex": "-",
    "Offset": 5,
    "Tone": "Tone",
    "rToneFreq": 94.8,
    "cToneFreq": 94.8,
    "DtcsCode": 23,
    "DtcsRxCode": 23,
    "DtcsPolarity": "NN",
    "Mode": "FM",
    "TStep": 5,
    "Comment": "CO Arapahoe Aurora N0ZUQ 448.4 OPEN On-Air"
  },
  {
    "Location": 8,
    "Name": "ZUQfortcollins,christmountain",
    "Frequency": 449.425,
    "Duplex": "-",
    "Offset": 5,
    "Tone": "Tone",
    "rToneFreq": 94.8,
    "cToneFreq": 94.8,
    "DtcsCode": 23,
    "DtcsRxCode": 23,
    "DtcsPolarity": "NN",
    "Mode": "FM",
    "TStep": 5,
    "Comment": "CO Larimer Fort Collins, Christ Mountain N0ZUQ 449.425 OPEN On-Air"
  },
  {
    "Location": 9,
    "Name": "ZUQfortcollins,christmountain",
    "Frequency": 927.875,
    "Duplex": "-",
    "Offset": 25,
    "Tone": "DTCS",
    "rToneFreq": 88.5,
    "cToneFreq": 88.5,
    "DtcsCode": 114,
    "DtcsRxCode": 114,
    "DtcsPolarity": "NN",
    "Mode": "FM",
    "TStep": 5,
    "Comment": "CO Larimer Fort Collins, Christ Mountain N0ZUQ WA6IMI 927.875 OPEN Off-Air"
  },
  {
    "Location": 10,
    "Name": "0BGaurora",
    "Frequency": 448.275,
    "Duplex": "-",
    "Offset": 5,
    "Tone": "Tone",
    "rToneFreq": 156.7,
    "cToneFreq": 156.7,
    "DtcsCode": 23,
    "DtcsRxCode": 23,
    "DtcsPolarity": "NN",
    "Mode": "FM",
    "TStep": 5,
    "Comment": "CO Arapahoe Aurora W0BG W0BG 448.275 OPEN On-Air"
  },
  {
    "Location": 11,
    "Name": "ANTaurora",
    "Frequency": 448.825,
    "Duplex": "-",
    "Offset": 5,
    "Tone": "",
    "rToneFreq": 88.5,
    "cToneFreq": 88.5,
    "DtcsCode": 23,
    "DtcsRxCode": 23,
    "DtcsPolarity": "NN",
    "Mode": "DIG",
    "TStep": 5,
    "Comment": "CO Arapahoe Aurora WN7ANT 448.825 OPEN On-Air"
  },
  {
    "Location": 12,
    "Name": "UDDaurora,smokeyhill",
    "Frequency": 448.5,
    "Duplex": "-",
    "Offset": 5,
    "Tone": "Tone",
    "rToneFreq": 100,
    "cToneFreq": 100,
    "DtcsCode": 23,
    "DtcsRxCode": 23,
    "DtcsPolarity": "NN",
    "Mode": "FM",
    "TStep": 5,
    "Comment": "CO Denver Aurora, Smokey Hill KB0UDD Castle Rock Repeater Group 448.5 OPEN On-Air"
  },
  {
    "Location": 13,
    "Name": "UDDaurora,smokyhill",
    "Frequency": 145.4,
    "Duplex": "-",
    "Offset": 0.6,
    "Tone": "Tone",
    "rToneFreq": 100,
    "cToneFreq": 100,
    "DtcsCode": 23,
    "DtcsRxCode": 23,
    "DtcsPolarity": "NN",
    "Mode": "FM",
    "TStep": 5,
    "Comment": "CO Arapahoe Aurora, Smoky Hill KB0UDD Castle Rock Repeater Group 145.4 OPEN On-Air"
  },
  {
    "Location": 14,
    "Name": "UDDidahosprings,squawmountain",
    "Frequency": 146.67,
    "Duplex": "-",
    "Offset": 0.6,
    "Tone": "Tone",
    "rToneFreq": 100,
    "cToneFreq": 100,
    "DtcsCode": 23,
    "DtcsRxCode": 23,
    "DtcsPolarity": "NN",
    "Mode": "FM",
    "TStep": 5,
    "Comment": "CO Clear Creek Idaho Springs, Squaw Mountain KB0UDD Castle Rock Repeater Group 146.67 OPEN On-Air"
  },
  {
    "Location": 15,
    "Name": "Q8Mparker",
    "Frequency": 448.7,
    "Duplex": "-",
    "Offset": 5,
    "Tone": "Tone",
    "rToneFreq": 146.2,
    "cToneFreq": 146.2,
    "DtcsCode": 23,
    "DtcsRxCode": 23,
    "DtcsPolarity": "NN",
    "Mode": "FM",
    "TStep": 5,
    "Comment": "CO Douglas Parker WQ8M 448.7 OPEN On-Air"
  },
  {
    "Location": 16,
    "Name": "OBAaurora",
    "Frequency": 145.19,
    "Duplex": "-",
    "Offset": 0.6,
    "Tone": "Tone",
    "rToneFreq": 151.4,
    "cToneFreq": 131.8,
    "DtcsCode": 23,
    "DtcsRxCode": 23,
    "DtcsPolarity": "NN",
    "Mode": "FM",
    "TStep": 5,
    "Comment": "CO Arapahoe Aurora N0OBA N0OBA 145.19 OPEN On-Air"
  },
  {
    "Location": 17,
    "Name": "FEZdenver",
    "Frequency": 447.925,
    "Duplex": "-",
    "Offset": 5,
    "Tone": "Tone",
    "rToneFreq": 100,
    "cToneFreq": 100,
    "DtcsCode": 23,
    "DtcsRxCode": 23,
    "DtcsPolarity": "NN",
    "Mode": "FM",
    "TStep": 5,
    "Comment": "CO Denver Denver K0FEZ RADOPS El Jebel Shriners 447.925 OPEN On-Air"
  },
  {
    "Location": 18,
    "Name": "FEZgolden,centennialcone",
    "Frequency": 146.985,
    "Duplex": "-",
    "Offset": 0.6,
    "Tone": "Tone",
    "rToneFreq": 100,
    "cToneFreq": 100,
    "DtcsCode": 23,
    "DtcsRxCode": 23,
    "DtcsPolarity": "NN",
    "Mode": "FM",
    "TStep": 5,
    "Comment": "CO Denver Golden, Centennial Cone K0FEZ El Jebel RADOPS 146.985 OPEN On-Air"
  },
  {
    "Location": 19,
    "Name": "TPTdenver",
    "Frequency": 447.9,
    "Duplex": "-",
    "Offset": 5,
    "Tone": "",
    "rToneFreq": 88.5,
    "cToneFreq": 88.5,
    "DtcsCode": 23,
    "DtcsRxCode": 23,
    "DtcsPolarity": "NN",
    "Mode": "FM",
    "TStep": 5,
    "Comment": "CO Denver Denver WB0TPT WB0TPT 447.9 OPEN Off-Air"
  },
  {
    "Location": 20,
    "Name": "0SJboulder,bluemountain",
    "Frequency": 145.475,
    "Duplex": "-",
    "Offset": 0.6,
    "Tone": "Tone",
    "rToneFreq": 100,
    "cToneFreq": 100,
    "DtcsCode": 23,
    "DtcsRxCode": 23,
    "DtcsPolarity": "NN",
    "Mode": "FM",
    "TStep": 5,
    "Comment": "CO Jefferson Boulder, Blue Mountain KE0SJ Intermountain Repeater Group 145.475 OPEN On-Air"
  },
  {
    "Location": 21,
    "Name": "0SJlochbuie",
    "Frequency": 447.625,
    "Duplex": "-",
    "Offset": 5,
    "Tone": "Tone",
    "rToneFreq": 100,
    "cToneFreq": 100,
    "DtcsCode": 23,
    "DtcsRxCode": 23,
    "DtcsPolarity": "NN",
    "Mode": "FM",
    "TStep": 5,
    "Comment": "CO Adams Lochbuie KE0SJ Intermountain Repeater Group 447.625 OPEN On-Air"
  },
  {
    "Location": 22,
    "Name": "0SJgolden,centennialcone",
    "Frequency": 145.28,
    "Duplex": "-",
    "Offset": 0.6,
    "Tone": "Tone",
    "rToneFreq": 100,
    "cToneFreq": 100,
    "DtcsCode": 23,
    "DtcsRxCode": 23,
    "DtcsPolarity": "NN",
    "Mode": "FM",
    "TStep": 5,
    "Comment": "CO Jefferson Golden, Centennial Cone KE0SJ 145.28 OPEN On-Air"
  },
  {
    "Location": 23,
    "Name": "0SJgolden,centennialcone",
    "Frequency": 449.525,
    "Duplex": "-",
    "Offset": 5,
    "Tone": "",
    "rToneFreq": 88.5,
    "cToneFreq": 88.5,
    "DtcsCode": 23,
    "DtcsRxCode": 23,
    "DtcsPolarity": "NN",
    "Mode": "FM",
    "TStep": 5,
    "Comment": "CO Jefferson Golden, Centennial Cone KE0SJ KE0SJ 449.525 OPEN On-Air"
  },
  {
    "Location": 24,
    "Name": "JXNdenver",
    "Frequency": 146.715,
    "Duplex": "-",
    "Offset": 0.6,
    "Tone": "Tone",
    "rToneFreq": 123,
    "cToneFreq": 123,
    "DtcsCode": 23,
    "DtcsRxCode": 23,
    "DtcsPolarity": "NN",
    "Mode": "FM",
    "TStep": 5,
    "Comment": "CO Denver Denver N0JXN EARS 146.715 OPEN On-Air"
  },
  {
    "Location": 25,
    "Name": "EHPdenver",
    "Frequency": 448.075,
    "Duplex": "-",
    "Offset": 5,
    "Tone": "Tone",
    "rToneFreq": 123,
    "cToneFreq": 123,
    "DtcsCode": 23,
    "DtcsRxCode": 23,
    "DtcsPolarity": "NN",
    "Mode": "FM",
    "TStep": 5,
    "Comment": "CO Denver Denver N5EHP W0IG 448.075 OPEN On-Air"
  },
  {
    "Location": 26,
    "Name": "KIZdenver",
    "Frequency": 448.55,
    "Duplex": "-",
    "Offset": 5,
    "Tone": "Tone",
    "rToneFreq": 82.5,
    "cToneFreq": 82.5,
    "DtcsCode": 23,
    "DtcsRxCode": 23,
    "DtcsPolarity": "NN",
    "Mode": "FM",
    "TStep": 5,
    "Comment": "CO Denver Denver W0KIZ HPRA 448.55 OPEN Off-Air"
  },
  {
    "Location": 27,
    "Name": "ESQparker,hessreservoir",
    "Frequency": 447.525,
    "Duplex": "-",
    "Offset": 5,
    "Tone": "Tone",
    "rToneFreq": 203.5,
    "cToneFreq": 146.2,
    "DtcsCode": 23,
    "DtcsRxCode": 23,
    "DtcsPolarity": "NN",
    "Mode": "FM",
    "TStep": 5,
    "Comment": "CO Douglas Parker, Hess Reservoir N0ESQ EmComm Colorado Colorado ARES 447.525 OPEN On-Air"
  },
  {
    "Location": 28,
    "Name": "ESQcastlerock,devilshead",
    "Frequency": 446.925,
    "Duplex": "-",
    "Offset": 5,
    "Tone": "",
    "rToneFreq": 88.5,
    "cToneFreq": 88.5,
    "DtcsCode": 23,
    "DtcsRxCode": 23,
    "DtcsPolarity": "NN",
    "Mode": "DMR",
    "TStep": 5,
    "Comment": "CO Douglas Castle Rock, Devils Head N0ESQ 446.925 OPEN On-Air"
  },
  {
    "Location": 29,
    "Name": "ESQcastlerock,devilshead(pikenationalforest)",
    "Frequency": 447.525,
    "Duplex": "-",
    "Offset": 5,
    "Tone": "Tone",
    "rToneFreq": 146.2,
    "cToneFreq": 146.2,
    "DtcsCode": 23,
    "DtcsRxCode": 23,
    "DtcsPolarity": "NN",
    "Mode": "FM",
    "TStep": 5,
    "Comment": "CO Douglas Castle Rock, Devils Head (Pike National Forest) N0ESQ EmComm Colorado Colorado ARES 447.525 OPEN On-Air"
  },
  {
    "Location": 30,
    "Name": "9SLcastlepines,danielspark",
    "Frequency": 449.95,
    "Duplex": "-",
    "Offset": 5,
    "Tone": "Tone",
    "rToneFreq": 77,
    "cToneFreq": 77,
    "DtcsCode": 23,
    "DtcsRxCode": 23,
    "DtcsPolarity": "NN",
    "Mode": "FM",
    "TStep": 5,
    "Comment": "CO Douglas Castle Pines, Daniels Park W9SL W9SL Owner 449.95 OPEN On-Air"
  },
  {
    "Location": 31,
    "Name": "JRLdenver,broadwayplazalofts",
    "Frequency": 447.175,
    "Duplex": "-",
    "Offset": 5,
    "Tone": "Tone",
    "rToneFreq": 100,
    "cToneFreq": 100,
    "DtcsCode": 23,
    "DtcsRxCode": 23,
    "DtcsPolarity": "NN",
    "Mode": "FM",
    "TStep": 5,
    "Comment": "CO Denver Denver, Broadway Plaza Lofts W0JRL W0JRL 447.175 OPEN On-Air"
  },
  {
    "Location": 32,
    "Name": "PWOcentennial",
    "Frequency": 449.425,
    "Duplex": "-",
    "Offset": 5,
    "Tone": "DTCS",
    "rToneFreq": 88.5,
    "cToneFreq": 88.5,
    "DtcsCode": 23,
    "DtcsRxCode": 23,
    "DtcsPolarity": "NN",
    "Mode": "FM",
    "TStep": 5,
    "Comment": "CO Arapahoe Centennial K0PWO K0PWO 449.425 OPEN Off-Air"
  },
  {
    "Location": 33,
    "Name": "GURdenver,greenvalleyranch",
    "Frequency": 448.15,
    "Duplex": "-",
    "Offset": 5,
    "Tone": "Tone",
    "rToneFreq": 141.3,
    "cToneFreq": 141.3,
    "DtcsCode": 23,
    "DtcsRxCode": 23,
    "DtcsPolarity": "NN",
    "Mode": "FM",
    "TStep": 5,
    "Comment": "CO Denver Denver, Green Valley Ranch K0GUR K0GUR 448.15 OPEN On-Air"
  },
  {
    "Location": 34,
    "Name": "ELYlakewood",
    "Frequency": 448.75,
    "Duplex": "-",
    "Offset": 5,
    "Tone": "Tone",
    "rToneFreq": 100,
    "cToneFreq": 100,
    "DtcsCode": 23,
    "DtcsRxCode": 23,
    "DtcsPolarity": "NN",
    "Mode": "FM",
    "TStep": 5,
    "Comment": "CO Jefferson Lakewood N0ELY N0ELY 448.75 OPEN On-Air"
  },
  {
    "Location": 35,
    "Name": "0TXlakewood,stanthonymedicalcampus",
    "Frequency": 447.825,
    "Duplex": "-",
    "Offset": 5,
    "Tone": "DTCS",
    "rToneFreq": 88.5,
    "cToneFreq": 88.5,
    "DtcsCode": 73,
    "DtcsRxCode": 73,
    "DtcsPolarity": "NN",
    "Mode": "NFM",
    "TStep": 5,
    "Comment": "CO Jefferson Lakewood, St Anthony Medical Campus W0TX Denver Radio Club 447.825 OPEN On-Air"
  },
  {
    "Location": 36,
    "Name": "0TXlakewood,greenmountain",
    "Frequency": 147.33,
    "Duplex": "+",
    "Offset": 0.6,
    "Tone": "Tone",
    "rToneFreq": 100,
    "cToneFreq": 100,
    "DtcsCode": 23,
    "DtcsRxCode": 23,
    "DtcsPolarity": "NN",
    "Mode": "FM",
    "TStep": 5,
    "Comment": "CO Jefferson Lakewood, Green Mountain W0TX Denver Radio Club 147.33 OPEN On-Air"
  },
  {
    "Location": 37,
    "Name": "0TXlakewood,greenmountain",
    "Frequency": 224.38,
    "Duplex": "-",
    "Offset": 1.6,
    "Tone": "Tone",
    "rToneFreq": 100,
    "cToneFreq": 100,
    "DtcsCode": 23,
    "DtcsRxCode": 23,
    "DtcsPolarity": "NN",
    "Mode": "FM",
    "TStep": 5,
    "Comment": "CO Jefferson Lakewood, Green Mountain W0TX Denver Radio Club 224.38 OPEN On-Air"
  },
  {
    "Location": 38,
    "Name": "0TXlakewood,greenmtn",
    "Frequency": 449.775,
    "Duplex": "-",
    "Offset": 5,
    "Tone": "Tone",
    "rToneFreq": 100,
    "cToneFreq": 100,
    "DtcsCode": 23,
    "DtcsRxCode": 23,
    "DtcsPolarity": "NN",
    "Mode": "DIG",
    "TStep": 5,
    "Comment": "CO Jefferson Lakewood, Green Mtn W0TX Denver Radio Club 449.775 OPEN On-Air"
  },
  {
    "Location": 39,
    "Name": "0TXlakewood,greenmountain",
    "Frequency": 53.09,
    "Duplex": "-",
    "Offset": 1.7,
    "Tone": "Tone",
    "rToneFreq": 107.2,
    "cToneFreq": 107.2,
    "DtcsCode": 23,
    "DtcsRxCode": 23,
    "DtcsPolarity": "NN",
    "Mode": "FM",
    "TStep": 5,
    "Comment": "CO Jefferson Lakewood, Green Mountain W0TX Denver Radio Club 53.09 OPEN On-Air"
  },
  {
    "Location": 40,
    "Name": "0TXgolden,centennialcone",
    "Frequency": 448.625,
    "Duplex": "-",
    "Offset": 5,
    "Tone": "Tone",
    "rToneFreq": 100,
    "cToneFreq": 100,
    "DtcsCode": 23,
    "DtcsRxCode": 23,
    "DtcsPolarity": "NN",
    "Mode": "FM",
    "TStep": 5,
    "Comment": "CO Jefferson Golden, Centennial Cone W0TX Denver Radio Club 448.625 OPEN On-Air"
  },
  {
    "Location": 41,
    "Name": "0TXdenver,centennialcone",
    "Frequency": 446.7875,
    "Duplex": "-",
    "Offset": 5,
    "Tone": "",
    "rToneFreq": 88.5,
    "cToneFreq": 88.5,
    "DtcsCode": 23,
    "DtcsRxCode": 23,
    "DtcsPolarity": "NN",
    "Mode": "DMR",
    "TStep": 5,
    "Comment": "CO Jefferson Denver, Centennial Cone W0TX Denver Radio Club Brandmeister Network 446.7875 OPEN On-Air"
  },
  {
    "Location": 42,
    "Name": "0TXidahosprings,centennialcone",
    "Frequency": 145.49,
    "Duplex": "-",
    "Offset": 0.6,
    "Tone": "Tone",
    "rToneFreq": 100,
    "cToneFreq": 100,
    "DtcsCode": 23,
    "DtcsRxCode": 23,
    "DtcsPolarity": "NN",
    "Mode": "FM",
    "TStep": 5,
    "Comment": "CO Jefferson Idaho Springs, Centennial Cone W0TX KB0VIU, Denver Radio Club 145.49 OPEN On-Air"
  },
  {
    "Location": 43,
    "Name": "0TXidahosprings,squawmountain",
    "Frequency": 449.35,
    "Duplex": "-",
    "Offset": 5,
    "Tone": "Tone",
    "rToneFreq": 100,
    "cToneFreq": 100,
    "DtcsCode": 23,
    "DtcsRxCode": 23,
    "DtcsPolarity": "NN",
    "Mode": "FM",
    "TStep": 5,
    "Comment": "CO Clear Creek Idaho Springs, Squaw Mountain W0TX Denver Radio Club 449.35 OPEN On-Air"
  },
  {
    "Location": 44,
    "Name": "UPSwestminster",
    "Frequency": 449.3,
    "Duplex": "-",
    "Offset": 5,
    "Tone": "Tone",
    "rToneFreq": 100,
    "cToneFreq": 100,
    "DtcsCode": 23,
    "DtcsRxCode": 23,
    "DtcsPolarity": "NN",
    "Mode": "FM",
    "TStep": 5,
    "Comment": "CO Adams Westminster N1UPS N1UPS 449.3 OPEN On-Air"
  },
  {
    "Location": 45,
    "Name": "SSPlakewood,moffattreatmentplant",
    "Frequency": 147.21,
    "Duplex": "+",
    "Offset": 0.6,
    "Tone": "Tone",
    "rToneFreq": 100,
    "cToneFreq": 100,
    "DtcsCode": 23,
    "DtcsRxCode": 23,
    "DtcsPolarity": "NN",
    "Mode": "FM",
    "TStep": 5,
    "Comment": "CO Jefferson Lakewood, Moffat Treatment Plant KD0SSP Denver Water Amateur Radio Club 147.21 OPEN On-Air"
  },
  {
    "Location": 46,
    "Name": "SSPlakewood,moffattreatmentplant",
    "Frequency": 448.35,
    "Duplex": "-",
    "Offset": 5,
    "Tone": "Tone",
    "rToneFreq": 225.7,
    "cToneFreq": 225.7,
    "DtcsCode": 23,
    "DtcsRxCode": 23,
    "DtcsPolarity": "NN",
    "Mode": "DIG",
    "TStep": 5,
    "Comment": "CO Jefferson Lakewood, Moffat Treatment Plant KD0SSP Denver Water Amateur Radio Club (DWARC) 448.35 OPEN On-Air"
  },
  {
    "Location": 47,
    "Name": "TUBcentennial,warrenmountain",
    "Frequency": 146.88,
    "Duplex": "-",
    "Offset": 0.6,
    "Tone": "Tone",
    "rToneFreq": 100,
    "cToneFreq": 100,
    "DtcsCode": 23,
    "DtcsRxCode": 23,
    "DtcsPolarity": "NN",
    "Mode": "FM",
    "TStep": 5,
    "Comment": "CO Jefferson Centennial, Warren Mountain WB0TUB Denver Radio League 146.88 OPEN On-Air"
  },
  {
    "Location": 48,
    "Name": "TUBcentennial,warrenmountain",
    "Frequency": 449.6,
    "Duplex": "-",
    "Offset": 5,
    "Tone": "Tone",
    "rToneFreq": 100,
    "cToneFreq": 100,
    "DtcsCode": 23,
    "DtcsRxCode": 23,
    "DtcsPolarity": "NN",
    "Mode": "FM",
    "TStep": 5,
    "Comment": "CO Jefferson Centennial, Warren Mountain WB0TUB Denver Radio League 449.6 OPEN On-Air"
  },
  {
    "Location": 49,
    "Name": "TUBgolden,centennialcone",
    "Frequency": 146.64,
    "Duplex": "-",
    "Offset": 0.6,
    "Tone": "Tone",
    "rToneFreq": 100,
    "cToneFreq": 100,
    "DtcsCode": 23,
    "DtcsRxCode": 23,
    "DtcsPolarity": "NN",
    "Mode": "FM",
    "TStep": 5,
    "Comment": "CO Jefferson Golden, Centennial Cone WB0TUB Denver Radio League 146.64 OPEN On-Air"
  },
  {
    "Location": 50,
    "Name": "PRAparker",
    "Frequency": 445.075,
    "Duplex": "-",
    "Offset": 5,
    "Tone": "",
    "rToneFreq": 88.5,
    "cToneFreq": 88.5,
    "DtcsCode": 23,
    "DtcsRxCode": 23,
    "DtcsPolarity": "NN",
    "Mode": "DMR",
    "TStep": 5,
    "Comment": "CO Douglas Parker K0PRA Parker Radio Association 445.075 OPEN On-Air"
  },
  {
    "Location": 51,
    "Name": "PRAfranktown",
    "Frequency": 446.85,
    "Duplex": "-",
    "Offset": 5,
    "Tone": "",
    "rToneFreq": 88.5,
    "cToneFreq": 88.5,
    "DtcsCode": 23,
    "DtcsRxCode": 23,
    "DtcsPolarity": "NN",
    "Mode": "DV",
    "TStep": 5,
    "Comment": "CO Douglas Franktown K0PRA Parker Radio Association 446.85 OPEN On-Air"
  },
  {
    "Location": 52,
    "Name": "0MLnorthglenn",
    "Frequency": 147.045,
    "Duplex": "+",
    "Offset": 0.6,
    "Tone": "Tone",
    "rToneFreq": 123,
    "cToneFreq": 123,
    "DtcsCode": 23,
    "DtcsRxCode": 23,
    "DtcsPolarity": "NN",
    "Mode": "FM",
    "TStep": 5,
    "Comment": "CO Adams Northglenn K0ML Northglenn RA 147.045 OPEN On-Air"
  },
  {
    "Location": 53,
    "Name": "0HCindianhills,chiefmtn",
    "Frequency": 927.9375,
    "Duplex": "-",
    "Offset": 25.9,
    "Tone": "",
    "rToneFreq": 88.5,
    "cToneFreq": 88.5,
    "DtcsCode": 23,
    "DtcsRxCode": 23,
    "DtcsPolarity": "NN",
    "Mode": "P25",
    "TStep": 5,
    "Comment": "CO Jefferson Indian Hills, Chief Mtn KI0HC 927.9375 OPEN On-Air"
  },
  {
    "Location": 54,
    "Name": "0HCparker",
    "Frequency": 927.8375,
    "Duplex": "-",
    "Offset": 25.8,
    "Tone": "Tone",
    "rToneFreq": 100,
    "cToneFreq": 100,
    "DtcsCode": 23,
    "DtcsRxCode": 23,
    "DtcsPolarity": "NN",
    "Mode": "P25",
    "TStep": 5,
    "Comment": "CO Douglas Parker KI0HC 927.8375 OPEN On-Air"
  },
  {
    "Location": 55,
    "Name": "0HCgolden,centennialcone",
    "Frequency": 927.8375,
    "Duplex": "-",
    "Offset": 25.8,
    "Tone": "DTCS",
    "rToneFreq": 88.5,
    "cToneFreq": 88.5,
    "DtcsCode": 205,
    "DtcsRxCode": 205,
    "DtcsPolarity": "NN",
    "Mode": "P25",
    "TStep": 5,
    "Comment": "CO Jefferson Golden, Centennial Cone KI0HC 927.8375 OPEN On-Air"
  },
  {
    "Location": 56,
    "Name": "LXXmorrison,mt.morrison",
    "Frequency": 53.17,
    "Duplex": "-",
    "Offset": 0.5,
    "Tone": "Tone",
    "rToneFreq": 107.2,
    "cToneFreq": 107.2,
    "DtcsCode": 23,
    "DtcsRxCode": 23,
    "DtcsPolarity": "NN",
    "Mode": "FM",
    "TStep": 5,
    "Comment": "CO Jefferson Morrison, Mt. Morrison N6LXX N6LXX N6LXX 53.17 OPEN On-Air"
  },
  {
    "Location": 57,
    "Name": "LXXmorrison,mt.morrison",
    "Frequency": 447.875,
    "Duplex": "-",
    "Offset": 5,
    "Tone": "Tone",
    "rToneFreq": 107.2,
    "cToneFreq": 107.2,
    "DtcsCode": 23,
    "DtcsRxCode": 23,
    "DtcsPolarity": "NN",
    "Mode": "FM",
    "TStep": 5,
    "Comment": "CO Jefferson Morrison, Mt. Morrison N6LXX N6LXX N6LXX 447.875 OPEN On-Air"
  },
  {
    "Location": 58,
    "Name": "OWYconifer,critchellmountain",
    "Frequency": 447.5,
    "Duplex": "-",
    "Offset": 5,
    "Tone": "Tone",
    "rToneFreq": 88.5,
    "cToneFreq": 88.5,
    "DtcsCode": 23,
    "DtcsRxCode": 23,
    "DtcsPolarity": "NN",
    "Mode": "FM",
    "TStep": 5,
    "Comment": "CO Jefferson Conifer, Critchell Mountain N0OWY Aurora Repeater Association 447.5 OPEN On-Air"
  },
  {
    "Location": 59,
    "Name": "PYYgolden",
    "Frequency": 927.7875,
    "Duplex": "-",
    "Offset": 25,
    "Tone": "Tone",
    "rToneFreq": 156.7,
    "cToneFreq": 156.7,
    "DtcsCode": 23,
    "DtcsRxCode": 23,
    "DtcsPolarity": "NN",
    "Mode": "FM",
    "TStep": 5,
    "Comment": "CO Jefferson Golden N0PYY N0PYY 927.7875 OPEN On-Air"
  },
  {
    "Location": 60,
    "Name": "PYYgolden",
    "Frequency": 448.125,
    "Duplex": "-",
    "Offset": 5,
    "Tone": "Tone",
    "rToneFreq": 107.2,
    "cToneFreq": 107.2,
    "DtcsCode": 23,
    "DtcsRxCode": 23,
    "DtcsPolarity": "NN",
    "Mode": "FM",
    "TStep": 5,
    "Comment": "CO Jefferson Golden N0PYY Denver PD EEB 448.125 OPEN On-Air"
  },
  {
    "Location": 61,
    "Name": "PYYevergreen,squawmountain",
    "Frequency": 147.3,
    "Duplex": "+",
    "Offset": 0.6,
    "Tone": "Tone",
    "rToneFreq": 103.5,
    "cToneFreq": 103.5,
    "DtcsCode": 23,
    "DtcsRxCode": 23,
    "DtcsPolarity": "NN",
    "Mode": "FM",
    "TStep": 5,
    "Comment": "CO Clear Creek Evergreen, Squaw Mountain N0PYY Denver PD EEB 147.3 OPEN On-Air"
  },
  {
    "Location": 62,
    "Name": "0GVgolden",
    "Frequency": 448.975,
    "Duplex": "-",
    "Offset": 5,
    "Tone": "Tone",
    "rToneFreq": 123,
    "cToneFreq": 123,
    "DtcsCode": 23,
    "DtcsRxCode": 23,
    "DtcsPolarity": "NN",
    "Mode": "FM",
    "TStep": 5,
    "Comment": "CO Jefferson Golden W0GV FRG 448.975 OPEN On-Air"
  },
  {
    "Location": 63,
    "Name": "WYXbroomfield",
    "Frequency": 449.825,
    "Duplex": "-",
    "Offset": 5,
    "Tone": "Tone",
    "rToneFreq": 103.5,
    "cToneFreq": 103.5,
    "DtcsCode": 23,
    "DtcsRxCode": 23,
    "DtcsPolarity": "NN",
    "Mode": "FM",
    "TStep": 5,
    "Comment": "CO Boulder Broomfield W0WYX Rocky Mountain Radio League 449.825 OPEN On-Air"
  },
  {
    "Location": 64,
    "Name": "WYXidahosprings,squawmountain",
    "Frequency": 146.94,
    "Duplex": "-",
    "Offset": 0.6,
    "Tone": "Tone",
    "rToneFreq": 103.5,
    "cToneFreq": 103.5,
    "DtcsCode": 23,
    "DtcsRxCode": 23,
    "DtcsPolarity": "NN",
    "Mode": "FM",
    "TStep": 5,
    "Comment": "CO Clear Creek Idaho Springs, Squaw Mountain W0WYX Rocky Mtn Radio League 146.94 OPEN On-Air"
  },
  {
    "Location": 65,
    "Name": "LMAbroomfield",
    "Frequency": 448.925,
    "Duplex": "-",
    "Offset": 5,
    "Tone": "Tone",
    "rToneFreq": 131.8,
    "cToneFreq": 131.8,
    "DtcsCode": 23,
    "DtcsRxCode": 23,
    "DtcsPolarity": "NN",
    "Mode": "FM",
    "TStep": 5,
    "Comment": "CO Boulder Broomfield W0LMA W0LMA 448.925 OPEN On-Air"
  },
  {
    "Location": 66,
    "Name": "YZTgolden,lookout",
    "Frequency": 446.8375,
    "Duplex": "-",
    "Offset": 5,
    "Tone": "",
    "rToneFreq": 88.5,
    "cToneFreq": 88.5,
    "DtcsCode": 23,
    "DtcsRxCode": 23,
    "DtcsPolarity": "NN",
    "Mode": "DMR",
    "TStep": 5,
    "Comment": "CO Jefferson Golden, Lookout WA2YZT WA2YZT 446.8375 OPEN On-Air"
  },
  {
    "Location": 67,
    "Name": "CDSgolden,lookoutmountain",
    "Frequency": 145.25,
    "Duplex": "-",
    "Offset": 0.6,
    "Tone": "",
    "rToneFreq": 88.5,
    "cToneFreq": 88.5,
    "DtcsCode": 23,
    "DtcsRxCode": 23,
    "DtcsPolarity": "NN",
    "Mode": "DV",
    "TStep": 5,
    "Comment": "CO Jefferson Golden, Lookout Mountain W0CDS Colorado D-Star 145.25 OPEN On-Air"
  },
  {
    "Location": 68,
    "Name": "CDSgolden,lookoutmountain",
    "Frequency": 446.9625,
    "Duplex": "-",
    "Offset": 5,
    "Tone": "",
    "rToneFreq": 88.5,
    "cToneFreq": 88.5,
    "DtcsCode": 23,
    "DtcsRxCode": 23,
    "DtcsPolarity": "NN",
    "Mode": "DV",
    "TStep": 5,
    "Comment": "CO Jefferson Golden, Lookout Mountain W0CDS Colorado D-Star 446.9625 OPEN On-Air"
  },
  {
    "Location": 69,
    "Name": "CDSgolden,lookoutmountain",
    "Frequency": 1283.9625,
    "Duplex": "-",
    "Offset": 20,
    "Tone": "",
    "rToneFreq": 88.5,
    "cToneFreq": 88.5,
    "DtcsCode": 23,
    "DtcsRxCode": 23,
    "DtcsPolarity": "NN",
    "Mode": "DV",
    "TStep": 5,
    "Comment": "CO Jefferson Golden, Lookout Mountain W0CDS Colorado D-Star 1283.9625 OPEN On-Air"
  },
  {
    "Location": 70,
    "Name": "CDSgolden,lookoutmountain",
    "Frequency": 1299.9,
    "Duplex": "",
    "Offset": 0,
    "Tone": "",
    "rToneFreq": 88.5,
    "cToneFreq": 88.5,
    "DtcsCode": 23,
    "DtcsRxCode": 23,
    "DtcsPolarity": "NN",
    "Mode": "DV",
    "TStep": 5,
    "Comment": "CO Jefferson Golden, Lookout Mountain W0CDS Colorado D-Star 1299.9 OPEN On-Air"
  },
  {
    "Location": 71,
    "Name": "0SZgolden,lookoutmountain",
    "Frequency": 145.37,
    "Duplex": "-",
    "Offset": 0.6,
    "Tone": "",
    "rToneFreq": 88.5,
    "cToneFreq": 88.5,
    "DtcsCode": 23,
    "DtcsRxCode": 23,
    "DtcsPolarity": "NN",
    "Mode": "DMR",
    "TStep": 5,
    "Comment": "CO Jefferson Golden, Lookout Mountain N0SZ Rocky Mountain Ham Radio 145.37 OPEN On-Air"
  },
  {
    "Location": 72,
    "Name": "0SZevergreen,squawmountain",
    "Frequency": 145.175,
    "Duplex": "-",
    "Offset": 0.6,
    "Tone": "",
    "rToneFreq": 88.5,
    "cToneFreq": 88.5,
    "DtcsCode": 23,
    "DtcsRxCode": 23,
    "DtcsPolarity": "NN",
    "Mode": "DMR",
    "TStep": 5,
    "Comment": "CO Clear Creek Evergreen, Squaw Mountain N0SZ Rocky Mountain Ham Radio 145.175 OPEN On-Air"
  },
  {
    "Location": 73,
    "Name": "0SZboulder,mountthorodin",
    "Frequency": 446.8,
    "Duplex": "-",
    "Offset": 5,
    "Tone": "",
    "rToneFreq": 88.5,
    "cToneFreq": 88.5,
    "DtcsCode": 23,
    "DtcsRxCode": 23,
    "DtcsPolarity": "NN",
    "Mode": "DMR",
    "TStep": 5,
    "Comment": "CO Boulder Boulder, Mount Thorodin N0SZ Rocky Mountain Ham Radio Rocky Mountain Ham Radio 446.8 OPEN On-Air"
  },
  {
    "Location": 74,
    "Name": "0SZwestcreek",
    "Frequency": 446.875,
    "Duplex": "-",
    "Offset": 5,
    "Tone": "",
    "rToneFreq": 88.5,
    "cToneFreq": 88.5,
    "DtcsCode": 23,
    "DtcsRxCode": 23,
    "DtcsPolarity": "NN",
    "Mode": "DMR",
    "TStep": 5,
    "Comment": "CO Douglas Westcreek N0SZ W0VG RMHAM 446.875 OPEN On-Air"
  },
  {
    "Location": 75,
    "Name": "0SZdenver,thorodinmountain",
    "Frequency": 449.225,
    "Duplex": "-",
    "Offset": 5,
    "Tone": "Tone",
    "rToneFreq": 141.3,
    "cToneFreq": 141.3,
    "DtcsCode": 23,
    "DtcsRxCode": 23,
    "DtcsPolarity": "NN",
    "Mode": "FM",
    "TStep": 5,
    "Comment": "CO Gilpin Denver, Thorodin Mountain N0SZ Rocky Mountain Ham Radio (RMHR) 449.225 OPEN On-Air"
  },
  {
    "Location": 76,
    "Name": "0SZidahosprings,squawmountain",
    "Frequency": 448.225,
    "Duplex": "-",
    "Offset": 5,
    "Tone": "Tone",
    "rToneFreq": 141.3,
    "cToneFreq": 141.3,
    "DtcsCode": 23,
    "DtcsRxCode": 23,
    "DtcsPolarity": "NN",
    "Mode": "FM",
    "TStep": 5,
    "Comment": "CO Clear Creek Idaho Springs, Squaw Mountain N0SZ Rocky Mountain Ham Radio 448.225 OPEN On-Air"
  },
  {
    "Location": 77,
    "Name": "0SZidahosprings,squawmountain",
    "Frequency": 446.9375,
    "Duplex": "-",
    "Offset": 5,
    "Tone": "",
    "rToneFreq": 88.5,
    "cToneFreq": 88.5,
    "DtcsCode": 23,
    "DtcsRxCode": 23,
    "DtcsPolarity": "NN",
    "Mode": "DMR",
    "TStep": 5,
    "Comment": "CO Clear Creek Idaho Springs, Squaw Mountain N0SZ Rocky Mountain Ham Radio 446.9375 OPEN On-Air"
  },
  {
    "Location": 78,
    "Name": "0SZboulder,leehill",
    "Frequency": 445.05,
    "Duplex": "-",
    "Offset": 5,
    "Tone": "",
    "rToneFreq": 88.5,
    "cToneFreq": 88.5,
    "DtcsCode": 23,
    "DtcsRxCode": 23,
    "DtcsPolarity": "NN",
    "Mode": "DMR",
    "TStep": 5,
    "Comment": "CO Boulder Boulder, Lee Hill N0SZ Rocky Mountain Ham Radio 445.05 OPEN On-Air"
  },
  {
    "Location": 79,
    "Name": "0SZboulder,leehill",
    "Frequency": 446.9875,
    "Duplex": "-",
    "Offset": 5,
    "Tone": "",
    "rToneFreq": 88.5,
    "cToneFreq": 88.5,
    "DtcsCode": 23,
    "DtcsRxCode": 23,
    "DtcsPolarity": "NN",
    "Mode": "DMR",
    "TStep": 5,
    "Comment": "CO Boulder Boulder, Lee Hill N0SZ Rocky Mountain Ham Radio 446.9875 OPEN On-Air"
  },
  {
    "Location": 80,
    "Name": "0SZboulder,leehill",
    "Frequency": 447.75,
    "Duplex": "-",
    "Offset": 5,
    "Tone": "Tone",
    "rToneFreq": 141.3,
    "cToneFreq": 141.3,
    "DtcsCode": 23,
    "DtcsRxCode": 23,
    "DtcsPolarity": "NN",
    "Mode": "FM",
    "TStep": 5,
    "Comment": "CO Boulder Boulder, Lee Hill N0SZ Rocky Mountain Ham Radio 447.75 OPEN On-Air"
  },
  {
    "Location": 81,
    "Name": "0SZcoloradosprings,almagremountain",
    "Frequency": 145.235,
    "Duplex": "-",
    "Offset": 0.6,
    "Tone": "",
    "rToneFreq": 88.5,
    "cToneFreq": 88.5,
    "DtcsCode": 23,
    "DtcsRxCode": 23,
    "DtcsPolarity": "NN",
    "Mode": "DMR",
    "TStep": 5,
    "Comment": "CO El Paso Colorado Springs, Almagre Mountain N0SZ RMHAM 145.235 OPEN On-Air"
  },
  {
    "Location": 82,
    "Name": "0SZcoloradosprings,cheyennemountain",
    "Frequency": 445.0625,
    "Duplex": "-",
    "Offset": 5,
    "Tone": "",
    "rToneFreq": 88.5,
    "cToneFreq": 88.5,
    "DtcsCode": 23,
    "DtcsRxCode": 23,
    "DtcsPolarity": "NN",
    "Mode": "DMR",
    "TStep": 5,
    "Comment": "CO El Paso Colorado Springs, Cheyenne Mountain N0SZ Rocky Mountain Ham Radio N0SZ Colorado Springs Brandmeister 445.0625 OPEN On-Air"
  },
  {
    "Location": 83,
    "Name": "0SZbreckenridge,baldy",
    "Frequency": 445.0875,
    "Duplex": "-",
    "Offset": 5,
    "Tone": "",
    "rToneFreq": 88.5,
    "cToneFreq": 88.5,
    "DtcsCode": 23,
    "DtcsRxCode": 23,
    "DtcsPolarity": "NN",
    "Mode": "DMR",
    "TStep": 5,
    "Comment": "CO Fremont Breckenridge, Baldy N0SZ K2AD Rocky Mountain Ham Radio 445.0875 OPEN On-Air"
  },
  {
    "Location": 84,
    "Name": "0SZfairplay,badger",
    "Frequency": 446.7625,
    "Duplex": "-",
    "Offset": 5,
    "Tone": "",
    "rToneFreq": 88.5,
    "cToneFreq": 88.5,
    "DtcsCode": 23,
    "DtcsRxCode": 23,
    "DtcsPolarity": "NN",
    "Mode": "DMR",
    "TStep": 5,
    "Comment": "CO Park Fairplay, Badger N0SZ K7PFJ RMHAM 446.7625 OPEN On-Air"
  },
  {
    "Location": 85,
    "Name": "0SZleadville,mosquitopass",
    "Frequency": 445.05,
    "Duplex": "-",
    "Offset": 5,
    "Tone": "",
    "rToneFreq": 88.5,
    "cToneFreq": 88.5,
    "DtcsCode": 23,
    "DtcsRxCode": 23,
    "DtcsPolarity": "NN",
    "Mode": "DMR",
    "TStep": 5,
    "Comment": "CO Lake Leadville, Mosquito Pass N0SZ K2AD Rocky Mountain Ham Radio 445.05 OPEN On-Air"
  },
  {
    "Location": 86,
    "Name": "0SZvail",
    "Frequency": 445.075,
    "Duplex": "-",
    "Offset": 5,
    "Tone": "",
    "rToneFreq": 88.5,
    "cToneFreq": 88.5,
    "DtcsCode": 23,
    "DtcsRxCode": 23,
    "DtcsPolarity": "NN",
    "Mode": "DMR",
    "TStep": 5,
    "Comment": "CO Eagle Vail N0SZ K2AD Rocky Mountain Ham Radio 445.075 OPEN On-Air"
  },
  {
    "Location": 87,
    "Name": "0SZsalida,methodistmountain",
    "Frequency": 446.8125,
    "Duplex": "-",
    "Offset": 5,
    "Tone": "",
    "rToneFreq": 88.5,
    "cToneFreq": 88.5,
    "DtcsCode": 23,
    "DtcsRxCode": 23,
    "DtcsPolarity": "NN",
    "Mode": "DMR",
    "TStep": 5,
    "Comment": "CO Chaffee Salida, Methodist Mountain N0SZ RMHAM 446.8125 OPEN On-Air"
  },
  {
    "Location": 88,
    "Name": "0SZdurango,missionaryridge",
    "Frequency": 445.1375,
    "Duplex": "-",
    "Offset": 5,
    "Tone": "",
    "rToneFreq": 88.5,
    "cToneFreq": 88.5,
    "DtcsCode": 23,
    "DtcsRxCode": 23,
    "DtcsPolarity": "NN",
    "Mode": "DMR",
    "TStep": 5,
    "Comment": "CO La Plata Durango, Missionary Ridge N0SZ K2AD Rocky Mountain Ham Radio 445.1375 OPEN On-Air"
  },
  {
    "Location": 89,
    "Name": "0SZrangely,cathedralbluffs",
    "Frequency": 445.2625,
    "Duplex": "-",
    "Offset": 5,
    "Tone": "",
    "rToneFreq": 88.5,
    "cToneFreq": 88.5,
    "DtcsCode": 23,
    "DtcsRxCode": 23,
    "DtcsPolarity": "NN",
    "Mode": "DMR",
    "TStep": 5,
    "Comment": "CO Rio Blanco Rangely, Cathedral Bluffs N0SZ RMHAM 445.2625 OPEN On-Air"
  },
  {
    "Location": 90,
    "Name": "VGDgolden,tablemountain",
    "Frequency": 446.975,
    "Duplex": "-",
    "Offset": 5,
    "Tone": "",
    "rToneFreq": 88.5,
    "cToneFreq": 88.5,
    "DtcsCode": 23,
    "DtcsRxCode": 23,
    "DtcsPolarity": "NN",
    "Mode": "DMR",
    "TStep": 5,
    "Comment": "CO Jefferson Golden, Table Mountain KB0VGD W0DMR 446.975 OPEN On-Air"
  },
  {
    "Location": 91,
    "Name": "VGDfortcollins,horsetoothmountain",
    "Frequency": 145.265,
    "Duplex": "-",
    "Offset": 0.6,
    "Tone": "",
    "rToneFreq": 88.5,
    "cToneFreq": 88.5,
    "DtcsCode": 23,
    "DtcsRxCode": 23,
    "DtcsPolarity": "NN",
    "Mode": "DMR",
    "TStep": 5,
    "Comment": "CO Larimer Fort Collins , Horsetooth Mountain KB0VGD W0DMR - NoCo C-bridge Network Brandmeister Network 145.265 OPEN On-Air"
  },
  {
    "Location": 92,
    "Name": "0KUgolden,lookoutmountain",
    "Frequency": 449.625,
    "Duplex": "-",
    "Offset": 5,
    "Tone": "Tone",
    "rToneFreq": 141.3,
    "cToneFreq": 141.3,
    "DtcsCode": 23,
    "DtcsRxCode": 23,
    "DtcsPolarity": "NN",
    "Mode": "FM",
    "TStep": 5,
    "Comment": "CO Jefferson Golden, Lookout Mountain W0KU Rocky Mountain Ham Radio 449.625 OPEN On-Air"
  },
  {
    "Location": 93,
    "Name": "0KCfortlupton",
    "Frequency": 447.3,
    "Duplex": "-",
    "Offset": 5,
    "Tone": "Tone",
    "rToneFreq": 107.2,
    "cToneFreq": 107.2,
    "DtcsCode": 23,
    "DtcsRxCode": 23,
    "DtcsPolarity": "NN",
    "Mode": "FM",
    "TStep": 5,
    "Comment": "CO Weld Fort Lupton AC0KC 447.3 OPEN On-Air"
  },
  {
    "Location": 94,
    "Name": "0KCfortlupton",
    "Frequency": 224.96,
    "Duplex": "-",
    "Offset": 1.6,
    "Tone": "",
    "rToneFreq": 88.5,
    "cToneFreq": 88.5,
    "DtcsCode": 23,
    "DtcsRxCode": 23,
    "DtcsPolarity": "NN",
    "Mode": "FM",
    "TStep": 5,
    "Comment": "CO Weld Fort Lupton AC0KC AC0KC 224.96 OPEN On-Air"
  },
  {
    "Location": 95,
    "Name": "GUQevergreen",
    "Frequency": 145.34,
    "Duplex": "-",
    "Offset": 0.6,
    "Tone": "Tone",
    "rToneFreq": 103.5,
    "cToneFreq": 127.3,
    "DtcsCode": 23,
    "DtcsRxCode": 23,
    "DtcsPolarity": "NN",
    "Mode": "FM",
    "TStep": 5,
    "Comment": "CO Jefferson Evergreen KE4GUQ Rocky Mtn Radio League 145.34 OPEN On-Air"
  },
  {
    "Location": 96,
    "Name": "CRAconifer,conifermountain",
    "Frequency": 224.98,
    "Duplex": "-",
    "Offset": 1.6,
    "Tone": "Tone",
    "rToneFreq": 107.2,
    "cToneFreq": 107.2,
    "DtcsCode": 23,
    "DtcsRxCode": 23,
    "DtcsPolarity": "NN",
    "Mode": "FM",
    "TStep": 5,
    "Comment": "CO Jefferson Conifer, Conifer Mountain W0CRA Colorado Repeater Association 224.98 OPEN Off-Air"
  },
  {
    "Location": 97,
    "Name": "CRAconifer,conifermountain",
    "Frequency": 447.15,
    "Duplex": "-",
    "Offset": 5,
    "Tone": "Tone",
    "rToneFreq": 107.2,
    "cToneFreq": 107.2,
    "DtcsCode": 23,
    "DtcsRxCode": 23,
    "DtcsPolarity": "NN",
    "Mode": "FM",
    "TStep": 5,
    "Comment": "CO Jefferson Conifer, Conifer Mountain W0CRA Colorado Repeater Association (CRA) 447.15 OPEN Off-Air"
  },
  {
    "Location": 98,
    "Name": "CRAconifer,conifermountain",
    "Frequency": 1287.9,
    "Duplex": "-",
    "Offset": 20,
    "Tone": "",
    "rToneFreq": 88.5,
    "cToneFreq": 88.5,
    "DtcsCode": 23,
    "DtcsRxCode": 23,
    "DtcsPolarity": "NN",
    "Mode": "FM",
    "TStep": 5,
    "Comment": "CO Jefferson Conifer, Conifer Mountain W0CRA Colorado Repeater Association (CRA) 1287.9 OPEN Off-Air"
  },
  {
    "Location": 99,
    "Name": "CRAlarkspur,westcreek",
    "Frequency": 147.225,
    "Duplex": "+",
    "Offset": 0.6,
    "Tone": "Tone",
    "rToneFreq": 107.2,
    "cToneFreq": 107.2,
    "DtcsCode": 23,
    "DtcsRxCode": 23,
    "DtcsPolarity": "NN",
    "Mode": "FM",
    "TStep": 5,
    "Comment": "CO Douglas Larkspur, Westcreek W0CRA Colorado Repeater Association (CRA) CRA VHF Link System 147.225 OPEN On-Air"
  },
  {
    "Location": 100,
    "Name": "CRAlarkspur,westcreek",
    "Frequency": 448.425,
    "Duplex": "-",
    "Offset": 5,
    "Tone": "Tone",
    "rToneFreq": 107.2,
    "cToneFreq": 107.2,
    "DtcsCode": 23,
    "DtcsRxCode": 23,
    "DtcsPolarity": "NN",
    "Mode": "FM",
    "TStep": 5,
    "Comment": "CO Douglas Larkspur, Westcreek W0CRA Colorado Repeater Association (CRA) ARESDEC 448.425 OPEN On-Air"
  },
  {
    "Location": 101,
    "Name": "CRAconifer,conifermountain",
    "Frequency": 53.05,
    "Duplex": "-",
    "Offset": 1.7,
    "Tone": "Tone",
    "rToneFreq": 107.2,
    "cToneFreq": 107.2,
    "DtcsCode": 23,
    "DtcsRxCode": 23,
    "DtcsPolarity": "NN",
    "Mode": "FM",
    "TStep": 5,
    "Comment": "CO Jefferson Conifer, Conifer Mountain W0CRA Colorado Repeater Association (CRA) 53.05 OPEN Off-Air"
  },
  {
    "Location": 102,
    "Name": "CRAidahosprings,squawmountain",
    "Frequency": 145.145,
    "Duplex": "-",
    "Offset": 0.6,
    "Tone": "Tone",
    "rToneFreq": 107.2,
    "cToneFreq": 107.2,
    "DtcsCode": 23,
    "DtcsRxCode": 23,
    "DtcsPolarity": "NN",
    "Mode": "FM",
    "TStep": 5,
    "Comment": "CO Clear Creek Idaho Springs, Squaw Mountain W0CRA Colorado Repeater Assoc 145.145 OPEN On-Air"
  },
  {
    "Location": 103,
    "Name": "CRAidahosprings,squawmountain",
    "Frequency": 447.575,
    "Duplex": "-",
    "Offset": 5,
    "Tone": "Tone",
    "rToneFreq": 107.2,
    "cToneFreq": 107.2,
    "DtcsCode": 23,
    "DtcsRxCode": 23,
    "DtcsPolarity": "NN",
    "Mode": "FM",
    "TStep": 5,
    "Comment": "CO Clear Creek Idaho Springs, Squaw Mountain W0CRA Colorado Repeater Association (CRA) 447.575 OPEN On-Air"
  },
  {
    "Location": 104,
    "Name": "CRAboulder,eldoradomountain",
    "Frequency": 145.46,
    "Duplex": "-",
    "Offset": 0.6,
    "Tone": "Tone",
    "rToneFreq": 107.2,
    "cToneFreq": 107.2,
    "DtcsCode": 23,
    "DtcsRxCode": 23,
    "DtcsPolarity": "NN",
    "Mode": "FM",
    "TStep": 5,
    "Comment": "CO Boulder Boulder, Eldorado Mountain W0CRA Colorado Repeater Association (CRA) CRA VHF Link System 145.46 OPEN On-Air"
  },
  {
    "Location": 105,
    "Name": "CRAboulder,eldoradomountain",
    "Frequency": 447.975,
    "Duplex": "-",
    "Offset": 5,
    "Tone": "Tone",
    "rToneFreq": 107.2,
    "cToneFreq": 107.2,
    "DtcsCode": 23,
    "DtcsRxCode": 23,
    "DtcsPolarity": "NN",
    "Mode": "FM",
    "TStep": 5,
    "Comment": "CO Boulder Boulder, Eldorado Mountain W0CRA Colorado Repeater Association (CRA) 447.975 OPEN On-Air"
  },
  {
    "Location": 106,
    "Name": "CRAcoloradosprings,cheyennemountain",
    "Frequency": 145.16,
    "Duplex": "-",
    "Offset": 0.6,
    "Tone": "Tone",
    "rToneFreq": 107.2,
    "cToneFreq": 107.2,
    "DtcsCode": 23,
    "DtcsRxCode": 23,
    "DtcsPolarity": "NN",
    "Mode": "FM",
    "TStep": 5,
    "Comment": "CO El Paso Colorado Springs, Cheyenne Mountain W0CRA Colorado Repeater Association CRA VHF Link System 145.16 OPEN On-Air"
  },
  {
    "Location": 107,
    "Name": "0GOgolden,guyhill",
    "Frequency": 449.75,
    "Duplex": "-",
    "Offset": 5,
    "Tone": "Tone",
    "rToneFreq": 103.5,
    "cToneFreq": 103.5,
    "DtcsCode": 23,
    "DtcsRxCode": 23,
    "DtcsPolarity": "NN",
    "Mode": "FM",
    "TStep": 5,
    "Comment": "CO Jefferson Golden, Guy Hill KI0GO Rocky Mtn Radio League 449.75 OPEN On-Air"
  },
  {
    "Location": 108,
    "Name": "POHgolden,guyhill",
    "Frequency": 224.74,
    "Duplex": "-",
    "Offset": 1.6,
    "Tone": "Tone",
    "rToneFreq": 88.5,
    "cToneFreq": 88.5,
    "DtcsCode": 23,
    "DtcsRxCode": 23,
    "DtcsPolarity": "NN",
    "Mode": "FM",
    "TStep": 5,
    "Comment": "CO Jefferson Golden, Guy Hill N0POH Aurora Repeater Assoc 224.74 OPEN On-Air"
  },
  {
    "Location": 109,
    "Name": "T0Cgolden,guyhill",
    "Frequency": 145.22,
    "Duplex": "-",
    "Offset": 0.6,
    "Tone": "Tone",
    "rToneFreq": 103.5,
    "cToneFreq": 103.5,
    "DtcsCode": 23,
    "DtcsRxCode": 23,
    "DtcsPolarity": "NN",
    "Mode": "P25",
    "TStep": 5,
    "Comment": "CO Jefferson Golden, Guy Hill WT0C Rocky Mtn Radio League 145.22 OPEN On-Air"
  },
  {
    "Location": 110,
    "Name": "IBMgolden,guyhill",
    "Frequency": 448.85,
    "Duplex": "-",
    "Offset": 5,
    "Tone": "Tone",
    "rToneFreq": 88.5,
    "cToneFreq": 88.5,
    "DtcsCode": 23,
    "DtcsRxCode": 23,
    "DtcsPolarity": "NN",
    "Mode": "FM",
    "TStep": 5,
    "Comment": "CO Jefferson Golden, Guy Hill K0IBM Aurora Repeater Assoc 448.85 OPEN On-Air"
  },
  {
    "Location": 111,
    "Name": "MHUgolden,guyhill",
    "Frequency": 224,
    "Duplex": "-",
    "Offset": 1.6,
    "Tone": "Tone",
    "rToneFreq": 103.5,
    "cToneFreq": 103.5,
    "DtcsCode": 23,
    "DtcsRxCode": 23,
    "DtcsPolarity": "NN",
    "Mode": "FM",
    "TStep": 5,
    "Comment": "CO Jefferson Golden, Guy Hill N0MHU Rocky Mountain Radio League 224 OPEN On-Air"
  },
  {
    "Location": 112,
    "Name": "CBIgolden,guyhill",
    "Frequency": 147.15,
    "Duplex": "+",
    "Offset": 0.6,
    "Tone": "Tone",
    "rToneFreq": 100,
    "cToneFreq": 100,
    "DtcsCode": 23,
    "DtcsRxCode": 23,
    "DtcsPolarity": "NN",
    "Mode": "FM",
    "TStep": 5,
    "Comment": "CO Jefferson Golden, Guy Hill W0CBI Aurora Repeater Assoc (ARA) 147.15 OPEN On-Air"
  },
  {
    "Location": 113,
    "Name": "ARAcritchell,critchellmountain",
    "Frequency": 147.12,
    "Duplex": "+",
    "Offset": 0.6,
    "Tone": "Tone",
    "rToneFreq": 88.5,
    "cToneFreq": 88.5,
    "DtcsCode": 23,
    "DtcsRxCode": 23,
    "DtcsPolarity": "NN",
    "Mode": "FM",
    "TStep": 5,
    "Comment": "CO Jefferson Critchell, Critchell Mountain N0ARA Aurora Repeater Association 147.12 OPEN On-Air"
  },
  {
    "Location": 114,
    "Name": "0EBhudson",
    "Frequency": 449.925,
    "Duplex": "-",
    "Offset": 5,
    "Tone": "Tone",
    "rToneFreq": 114.8,
    "cToneFreq": 114.8,
    "DtcsCode": 23,
    "DtcsRxCode": 23,
    "DtcsPolarity": "NN",
    "Mode": "FM",
    "TStep": 5,
    "Comment": "CO Weld Hudson K0EB K0EB K0UPS Club 449.925 OPEN On-Air"
  },
  {
    "Location": 115,
    "Name": "JSClarkspur,westcreek",
    "Frequency": 449.975,
    "Duplex": "-",
    "Offset": 5,
    "Tone": "Tone",
    "rToneFreq": 100,
    "cToneFreq": 100,
    "DtcsCode": 23,
    "DtcsRxCode": 23,
    "DtcsPolarity": "NN",
    "Mode": "FM",
    "TStep": 5,
    "Comment": "CO Douglas Larkspur, Westcreek K0JSC K0JSC The Fun Machine 449.975 OPEN On-Air"
  },
  {
    "Location": 116,
    "Name": "JSCcanoncity,canoncity",
    "Frequency": 449.975,
    "Duplex": "-",
    "Offset": 5,
    "Tone": "Tone",
    "rToneFreq": 100,
    "cToneFreq": 100,
    "DtcsCode": 23,
    "DtcsRxCode": 23,
    "DtcsPolarity": "NN",
    "Mode": "FM",
    "TStep": 5,
    "Comment": "CO Fremont Canon City, Canon City K0JSC K0JSC The Fun Machine 449.975 OPEN On-Air"
  },
  {
    "Location": 117,
    "Name": "JSCcanoncity,fremontpeak",
    "Frequency": 446.7375,
    "Duplex": "-",
    "Offset": 5,
    "Tone": "",
    "rToneFreq": 88.5,
    "cToneFreq": 88.5,
    "DtcsCode": 23,
    "DtcsRxCode": 23,
    "DtcsPolarity": "NN",
    "Mode": "DMR",
    "TStep": 5,
    "Comment": "CO Fremont Canon City, Fremont Peak K0JSC Rocky Mountain Ham Radio 446.7375 OPEN On-Air"
  },
  {
    "Location": 118,
    "Name": "JSCcanoncity,fremontpeak",
    "Frequency": 447.25,
    "Duplex": "-",
    "Offset": 5,
    "Tone": "Tone",
    "rToneFreq": 100,
    "cToneFreq": 100,
    "DtcsCode": 23,
    "DtcsRxCode": 23,
    "DtcsPolarity": "NN",
    "Mode": "FM",
    "TStep": 5,
    "Comment": "CO Fremont Canon City, Fremont Peak K0JSC 447.25 OPEN On-Air"
  },
  {
    "Location": 119,
    "Name": "JSCcanoncity,colorado",
    "Frequency": 447.975,
    "Duplex": "-",
    "Offset": 5,
    "Tone": "Tone",
    "rToneFreq": 100,
    "cToneFreq": 100,
    "DtcsCode": 23,
    "DtcsRxCode": 23,
    "DtcsPolarity": "NN",
    "Mode": "FM",
    "TStep": 5,
    "Comment": "CO Fremont Canon City, Colorado K0JSC K0JSC 447.975 OPEN On-Air"
  },
  {
    "Location": 120,
    "Name": "JSCpueblowest",
    "Frequency": 448.975,
    "Duplex": "-",
    "Offset": 5,
    "Tone": "Tone",
    "rToneFreq": 100,
    "cToneFreq": 100,
    "DtcsCode": 23,
    "DtcsRxCode": 23,
    "DtcsPolarity": "NN",
    "Mode": "FM",
    "TStep": 5,
    "Comment": "CO Pueblo Pueblo West K0JSC 448.975 OPEN On-Air"
  },
  {
    "Location": 121,
    "Name": "JSCpueblo",
    "Frequency": 446.9875,
    "Duplex": "-",
    "Offset": 5,
    "Tone": "",
    "rToneFreq": 88.5,
    "cToneFreq": 88.5,
    "DtcsCode": 23,
    "DtcsRxCode": 23,
    "DtcsPolarity": "NN",
    "Mode": "DMR",
    "TStep": 5,
    "Comment": "CO Pueblo Pueblo K0JSC RMHAM 446.9875 OPEN Off-Air"
  },
  {
    "Location": 122,
    "Name": "JSCpueblo,metro",
    "Frequency": 447.275,
    "Duplex": "-",
    "Offset": 5,
    "Tone": "Tone",
    "rToneFreq": 100,
    "cToneFreq": 100,
    "DtcsCode": 23,
    "DtcsRxCode": 23,
    "DtcsPolarity": "NN",
    "Mode": "FM",
    "TStep": 5,
    "Comment": "CO Pueblo Pueblo, Metro K0JSC The Fun Machine 447.275 OPEN On-Air"
  },
  {
    "Location": 123,
    "Name": "JSCwestcliffe",
    "Frequency": 448.325,
    "Duplex": "-",
    "Offset": 5,
    "Tone": "Tone",
    "rToneFreq": 100,
    "cToneFreq": 100,
    "DtcsCode": 23,
    "DtcsRxCode": 23,
    "DtcsPolarity": "NN",
    "Mode": "FM",
    "TStep": 5,
    "Comment": "CO Custer Westcliffe K0JSC The Fun Machine 448.325 OPEN On-Air"
  },
  {
    "Location": 124,
    "Name": "JSCsalida,methodistmountain",
    "Frequency": 449.975,
    "Duplex": "-",
    "Offset": 5,
    "Tone": "Tone",
    "rToneFreq": 100,
    "cToneFreq": 100,
    "DtcsCode": 23,
    "DtcsRxCode": 23,
    "DtcsPolarity": "NN",
    "Mode": "FM",
    "TStep": 5,
    "Comment": "CO Chaffee Salida, Methodist Mountain K0JSC 449.975 OPEN On-Air"
  },
  {
    "Location": 125,
    "Name": "JSCpueblo,cedarwood",
    "Frequency": 449.975,
    "Duplex": "-",
    "Offset": 5,
    "Tone": "Tone",
    "rToneFreq": 100,
    "cToneFreq": 100,
    "DtcsCode": 23,
    "DtcsRxCode": 23,
    "DtcsPolarity": "NN",
    "Mode": "FM",
    "TStep": 5,
    "Comment": "CO Pueblo Pueblo, Cedarwood K0JSC K0JSC 449.975 OPEN On-Air"
  },
  {
    "Location": 126,
    "Name": "XLFpalmerlake,monumenthill",
    "Frequency": 145.19,
    "Duplex": "-",
    "Offset": 0.6,
    "Tone": "Tone",
    "rToneFreq": 131.8,
    "cToneFreq": 131.8,
    "DtcsCode": 23,
    "DtcsRxCode": 23,
    "DtcsPolarity": "NN",
    "Mode": "FM",
    "TStep": 5,
    "Comment": "CO Douglas Palmer Lake, Monument Hill N0XLF N0OBA Owner 145.19 OPEN On-Air"
  },
  {
    "Location": 127,
    "Name": "0IAboulder,gunbarrelhill",
    "Frequency": 146.76,
    "Duplex": "-",
    "Offset": 0.6,
    "Tone": "Tone",
    "rToneFreq": 100,
    "cToneFreq": 100,
    "DtcsCode": 23,
    "DtcsRxCode": 23,
    "DtcsPolarity": "NN",
    "Mode": "FM",
    "TStep": 5,
    "Comment": "CO Boulder Boulder, Gunbarrel Hill W0IA Rocky Mtn VHF Soc Boulder County ARES 146.76 OPEN On-Air"
  },
  {
    "Location": 128,
    "Name": "0IAboulder",
    "Frequency": 449.55,
    "Duplex": "-",
    "Offset": 5,
    "Tone": "Tone",
    "rToneFreq": 100,
    "cToneFreq": 100,
    "DtcsCode": 23,
    "DtcsRxCode": 23,
    "DtcsPolarity": "NN",
    "Mode": "FM",
    "TStep": 5,
    "Comment": "CO Boulder Boulder W0IA Rocky Mtn VHF Soc 449.55 OPEN On-Air"
  },
  {
    "Location": 129,
    "Name": "0IAboulder,leehill",
    "Frequency": 224.02,
    "Duplex": "-",
    "Offset": 1.6,
    "Tone": "",
    "rToneFreq": 88.5,
    "cToneFreq": 88.5,
    "DtcsCode": 23,
    "DtcsRxCode": 23,
    "DtcsPolarity": "NN",
    "Mode": "FM",
    "TStep": 5,
    "Comment": "CO Boulder Boulder, Lee Hill W0IA Rocky Mtn VHF Soc 224.02 OPEN On-Air"
  },
  {
    "Location": 130,
    "Name": "0DKboulder,tablemesa",
    "Frequency": 448.9,
    "Duplex": "-",
    "Offset": 5,
    "Tone": "Tone",
    "rToneFreq": 100,
    "cToneFreq": 100,
    "DtcsCode": 23,
    "DtcsRxCode": 23,
    "DtcsPolarity": "NN",
    "Mode": "FM",
    "TStep": 5,
    "Comment": "CO Boulder Boulder, Table Mesa W0DK Boulder ARC 448.9 OPEN On-Air"
  },
  {
    "Location": 131,
    "Name": "0DKboulder",
    "Frequency": 146.61,
    "Duplex": "-",
    "Offset": 0.6,
    "Tone": "Tone",
    "rToneFreq": 100,
    "cToneFreq": 100,
    "DtcsCode": 23,
    "DtcsRxCode": 23,
    "DtcsPolarity": "NN",
    "Mode": "FM",
    "TStep": 5,
    "Comment": "CO Boulder Boulder W0DK Boulder Amateur Radio Club 146.61 OPEN Off-Air"
  },
  {
    "Location": 132,
    "Name": "0DKboulder,tablemountain",
    "Frequency": 146.7,
    "Duplex": "-",
    "Offset": 0.6,
    "Tone": "Tone",
    "rToneFreq": 100,
    "cToneFreq": 100,
    "DtcsCode": 23,
    "DtcsRxCode": 23,
    "DtcsPolarity": "NN",
    "Mode": "FM",
    "TStep": 5,
    "Comment": "CO Boulder Boulder, Table Mountain W0DK Boulder Co ARC 146.7 OPEN On-Air"
  },
  {
    "Location": 133,
    "Name": "0DKboulder",
    "Frequency": 1299.5,
    "Duplex": "-",
    "Offset": 20,
    "Tone": "",
    "rToneFreq": 88.5,
    "cToneFreq": 88.5,
    "DtcsCode": 23,
    "DtcsRxCode": 23,
    "DtcsPolarity": "NN",
    "Mode": "DV",
    "TStep": 5,
    "Comment": "CO Boulder Boulder W0DK Boulder County ARES 1299.5 OPEN On-Air"
  },
  {
    "Location": 134,
    "Name": "0DSboulder",
    "Frequency": 145.3875,
    "Duplex": "-",
    "Offset": 0.6,
    "Tone": "",
    "rToneFreq": 88.5,
    "cToneFreq": 88.5,
    "DtcsCode": 23,
    "DtcsRxCode": 23,
    "DtcsPolarity": "NN",
    "Mode": "DV",
    "TStep": 5,
    "Comment": "CO Boulder Boulder KC0DS Boulder County ARES 145.3875 OPEN On-Air"
  },
  {
    "Location": 135,
    "Name": "0DSboulder",
    "Frequency": 1283.8625,
    "Duplex": "-",
    "Offset": 20,
    "Tone": "",
    "rToneFreq": 88.5,
    "cToneFreq": 88.5,
    "DtcsCode": 23,
    "DtcsRxCode": 23,
    "DtcsPolarity": "NN",
    "Mode": "DV",
    "TStep": 5,
    "Comment": "CO Boulder Boulder KC0DS Boulder County ARES 1283.8625 OPEN On-Air"
  },
  {
    "Location": 136,
    "Name": "0DSboulder",
    "Frequency": 446.8625,
    "Duplex": "-",
    "Offset": 5,
    "Tone": "",
    "rToneFreq": 88.5,
    "cToneFreq": 88.5,
    "DtcsCode": 23,
    "DtcsRxCode": 23,
    "DtcsPolarity": "NN",
    "Mode": "DV",
    "TStep": 5,
    "Comment": "CO Boulder Boulder KC0DS Boulder County ARES 446.8625 OPEN On-Air"
  },
  {
    "Location": 137,
    "Name": "0NRmonument,monumenthill",
    "Frequency": 447.725,
    "Duplex": "-",
    "Offset": 5,
    "Tone": "Tone",
    "rToneFreq": 100,
    "cToneFreq": 100,
    "DtcsCode": 23,
    "DtcsRxCode": 23,
    "DtcsPolarity": "NN",
    "Mode": "FM",
    "TStep": 5,
    "Comment": "CO El Paso Monument, Monument Hill K0NR K0NR 447.725 OPEN On-Air"
  },
  {
    "Location": 138,
    "Name": "0DKboulder",
    "Frequency": 449.4,
    "Duplex": "-",
    "Offset": 5,
    "Tone": "Tone",
    "rToneFreq": 91.5,
    "cToneFreq": 91.5,
    "DtcsCode": 23,
    "DtcsRxCode": 23,
    "DtcsPolarity": "NN",
    "Mode": "FM",
    "TStep": 5,
    "Comment": "CO Boulder Boulder K0DK BARC 449.4 OPEN Off-Air"
  },
  {
    "Location": 139,
    "Name": "0DKboulder",
    "Frequency": 146.73,
    "Duplex": "-",
    "Offset": 0.6,
    "Tone": "Tone",
    "rToneFreq": 91.5,
    "cToneFreq": 91.5,
    "DtcsCode": 23,
    "DtcsRxCode": 23,
    "DtcsPolarity": "NN",
    "Mode": "FM",
    "TStep": 5,
    "Comment": "CO Boulder Boulder K0DK BARC 146.73 OPEN Off-Air"
  },
  {
    "Location": 140,
    "Name": "0KQevergreen,saddlebackmountain",
    "Frequency": 447.85,
    "Duplex": "-",
    "Offset": 5,
    "Tone": "Tone",
    "rToneFreq": 141.3,
    "cToneFreq": 141.3,
    "DtcsCode": 23,
    "DtcsRxCode": 23,
    "DtcsPolarity": "NN",
    "Mode": "FM",
    "TStep": 5,
    "Comment": "CO Clear Creek Evergreen, Saddleback Mountain AC0KQ AC0KQ Rocky Mountain Ham Radio 447.85 OPEN On-Air"
  },
  {
    "Location": 141,
    "Name": "ENOlongmont",
    "Frequency": 147.27,
    "Duplex": "+",
    "Offset": 0.6,
    "Tone": "Tone",
    "rToneFreq": 100,
    "cToneFreq": 100,
    "DtcsCode": 23,
    "DtcsRxCode": 23,
    "DtcsPolarity": "NN",
    "Mode": "FM",
    "TStep": 5,
    "Comment": "CO Boulder Longmont W0ENO Longmont ARC (LARC) 147.27 OPEN On-Air"
  },
  {
    "Location": 142,
    "Name": "ENOlongmont",
    "Frequency": 448.8,
    "Duplex": "-",
    "Offset": 5,
    "Tone": "Tone",
    "rToneFreq": 88.5,
    "cToneFreq": 88.5,
    "DtcsCode": 23,
    "DtcsRxCode": 23,
    "DtcsPolarity": "NN",
    "Mode": "FM",
    "TStep": 5,
    "Comment": "CO Boulder Longmont W0ENO Longmont ARC 448.8 OPEN On-Air"
  },
  {
    "Location": 143,
    "Name": "EPAlongmont",
    "Frequency": 448.525,
    "Duplex": "-",
    "Offset": 5,
    "Tone": "Tone",
    "rToneFreq": 151.4,
    "cToneFreq": 151.4,
    "DtcsCode": 23,
    "DtcsRxCode": 23,
    "DtcsPolarity": "NN",
    "Mode": "FM",
    "TStep": 5,
    "Comment": "CO Boulder Longmont N0EPA N0EPA 448.525 OPEN On-Air"
  },
  {
    "Location": 144,
    "Name": "VJJboulder,thorodinmountain",
    "Frequency": 145.31,
    "Duplex": "-",
    "Offset": 0.6,
    "Tone": "Tone",
    "rToneFreq": 88.5,
    "cToneFreq": 123,
    "DtcsCode": 23,
    "DtcsRxCode": 23,
    "DtcsPolarity": "NN",
    "Mode": "FM",
    "TStep": 5,
    "Comment": "CO Gilpin Boulder, Thorodin Mountain KB0VJJ Colorado Connection 145.31 OPEN On-Air"
  },
  {
    "Location": 145,
    "Name": "VJJcoloradosprings,cheyennemountain",
    "Frequency": 145.13,
    "Duplex": "-",
    "Offset": 0.6,
    "Tone": "Tone",
    "rToneFreq": 88.5,
    "cToneFreq": 123,
    "DtcsCode": 23,
    "DtcsRxCode": 23,
    "DtcsPolarity": "NN",
    "Mode": "FM",
    "TStep": 5,
    "Comment": "CO El Paso Colorado Springs, Cheyenne Mountain KB0VJJ Colorado Connection 145.13 OPEN On-Air"
  },
  {
    "Location": 146,
    "Name": "VJJwinterpark,winterpark",
    "Frequency": 147.285,
    "Duplex": "+",
    "Offset": 0.6,
    "Tone": "Tone",
    "rToneFreq": 88.5,
    "cToneFreq": 123,
    "DtcsCode": 23,
    "DtcsRxCode": 23,
    "DtcsPolarity": "NN",
    "Mode": "FM",
    "TStep": 5,
    "Comment": "CO Grand Winter Park, Winter Park KB0VJJ Colorado Connection 147.285 OPEN On-Air"
  },
  {
    "Location": 147,
    "Name": "VJJbreckenridge,baldmountain",
    "Frequency": 147.39,
    "Duplex": "+",
    "Offset": 0.6,
    "Tone": "Tone",
    "rToneFreq": 88.5,
    "cToneFreq": 123,
    "DtcsCode": 23,
    "DtcsRxCode": 23,
    "DtcsPolarity": "NN",
    "Mode": "FM",
    "TStep": 5,
    "Comment": "CO Summit Breckenridge, Bald Mountain KB0VJJ Colorado Connection 147.39 OPEN On-Air"
  },
  {
    "Location": 148,
    "Name": "VJJleadville,mosquitopass",
    "Frequency": 145.445,
    "Duplex": "-",
    "Offset": 0.6,
    "Tone": "Tone",
    "rToneFreq": 88.5,
    "cToneFreq": 88.5,
    "DtcsCode": 23,
    "DtcsRxCode": 23,
    "DtcsPolarity": "NN",
    "Mode": "FM",
    "TStep": 5,
    "Comment": "CO Lake Leadville, Mosquito Pass KB0VJJ Colorado Connection 145.445 OPEN On-Air"
  },
  {
    "Location": 149,
    "Name": "VJJkremmling,santoypeak",
    "Frequency": 147.075,
    "Duplex": "+",
    "Offset": 0.6,
    "Tone": "Tone",
    "rToneFreq": 88.5,
    "cToneFreq": 123,
    "DtcsCode": 23,
    "DtcsRxCode": 23,
    "DtcsPolarity": "NN",
    "Mode": "FM",
    "TStep": 5,
    "Comment": "CO Grand Kremmling, Santoy Peak KB0VJJ Colorado Connection 147.075 OPEN On-Air"
  },
  {
    "Location": 150,
    "Name": "VJJvail",
    "Frequency": 147.345,
    "Duplex": "+",
    "Offset": 0.6,
    "Tone": "Tone",
    "rToneFreq": 88.5,
    "cToneFreq": 123,
    "DtcsCode": 23,
    "DtcsRxCode": 23,
    "DtcsPolarity": "NN",
    "Mode": "FM",
    "TStep": 5,
    "Comment": "CO Eagle Vail KB0VJJ Colorado Connection 147.345 OPEN On-Air"
  },
  {
    "Location": 151,
    "Name": "VJJsalida,methodistmountain",
    "Frequency": 147.285,
    "Duplex": "+",
    "Offset": 0.6,
    "Tone": "Tone",
    "rToneFreq": 88.5,
    "cToneFreq": 123,
    "DtcsCode": 23,
    "DtcsRxCode": 23,
    "DtcsPolarity": "NN",
    "Mode": "FM",
    "TStep": 5,
    "Comment": "CO Chaffee Salida, Methodist Mountain KB0VJJ Colorado Connection 147.285 OPEN On-Air"
  },
  {
    "Location": 152,
    "Name": "VJJakron",
    "Frequency": 145.4,
    "Duplex": "-",
    "Offset": 0.6,
    "Tone": "Tone",
    "rToneFreq": 88.5,
    "cToneFreq": 123,
    "DtcsCode": 23,
    "DtcsRxCode": 23,
    "DtcsPolarity": "NN",
    "Mode": "FM",
    "TStep": 5,
    "Comment": "CO Washington Akron KB0VJJ Colorado Connection 145.4 OPEN On-Air"
  },
  {
    "Location": 153,
    "Name": "VJJwalden,petersonridge",
    "Frequency": 145.16,
    "Duplex": "-",
    "Offset": 0.6,
    "Tone": "Tone",
    "rToneFreq": 88.5,
    "cToneFreq": 123,
    "DtcsCode": 23,
    "DtcsRxCode": 23,
    "DtcsPolarity": "NN",
    "Mode": "FM",
    "TStep": 5,
    "Comment": "CO Jackson Walden, Peterson Ridge KB0VJJ Colorado Connection 145.16 OPEN On-Air"
  },
  {
    "Location": 154,
    "Name": "VJJsteamboatsprings",
    "Frequency": 147.165,
    "Duplex": "+",
    "Offset": 0.6,
    "Tone": "Tone",
    "rToneFreq": 88.5,
    "cToneFreq": 123,
    "DtcsCode": 23,
    "DtcsRxCode": 23,
    "DtcsPolarity": "NN",
    "Mode": "FM",
    "TStep": 5,
    "Comment": "CO Routt Steamboat Springs KB0VJJ Colorado Connection 147.165 OPEN On-Air"
  },
  {
    "Location": 155,
    "Name": "VJJsteamboatsprings",
    "Frequency": 449.625,
    "Duplex": "-",
    "Offset": 5,
    "Tone": "Tone",
    "rToneFreq": 123,
    "cToneFreq": 123,
    "DtcsCode": 23,
    "DtcsRxCode": 23,
    "DtcsPolarity": "NN",
    "Mode": "FM",
    "TStep": 5,
    "Comment": "CO Routt Steamboat Springs KB0VJJ Colorado Connection Repeaters, Inc. 449.625 OPEN On-Air"
  },
  {
    "Location": 156,
    "Name": "VJJglenwoodsprings,sunlightpeak",
    "Frequency": 146.85,
    "Duplex": "-",
    "Offset": 0.6,
    "Tone": "Tone",
    "rToneFreq": 88.5,
    "cToneFreq": 123,
    "DtcsCode": 23,
    "DtcsRxCode": 23,
    "DtcsPolarity": "NN",
    "Mode": "FM",
    "TStep": 5,
    "Comment": "CO Garfield Glenwood Springs, Sunlight Peak KB0VJJ Colorado Connection 146.85 OPEN On-Air"
  },
  {
    "Location": 157,
    "Name": "VJJcraig",
    "Frequency": 146.97,
    "Duplex": "-",
    "Offset": 0.6,
    "Tone": "Tone",
    "rToneFreq": 88.5,
    "cToneFreq": 123,
    "DtcsCode": 23,
    "DtcsRxCode": 23,
    "DtcsPolarity": "NN",
    "Mode": "FM",
    "TStep": 5,
    "Comment": "CO Moffat Craig KB0VJJ Northwest Colorado Amateur Radio Association Colorado Connection 146.97 OPEN On-Air"
  },
  {
    "Location": 158,
    "Name": "VJJgrandjunction,grandmesa",
    "Frequency": 145.355,
    "Duplex": "-",
    "Offset": 0.6,
    "Tone": "Tone",
    "rToneFreq": 88.5,
    "cToneFreq": 123,
    "DtcsCode": 23,
    "DtcsRxCode": 23,
    "DtcsPolarity": "NN",
    "Mode": "FM",
    "TStep": 5,
    "Comment": "CO Mesa Grand Junction, Grand Mesa KB0VJJ Colorado Connection 145.355 OPEN On-Air"
  },
  {
    "Location": 159,
    "Name": "VJJdurango,missionaryridge",
    "Frequency": 147.345,
    "Duplex": "+",
    "Offset": 0.6,
    "Tone": "Tone",
    "rToneFreq": 88.5,
    "cToneFreq": 123,
    "DtcsCode": 23,
    "DtcsRxCode": 23,
    "DtcsPolarity": "NN",
    "Mode": "FM",
    "TStep": 5,
    "Comment": "CO La Plata Durango, Missionary Ridge KB0VJJ Colorado Connection 147.345 OPEN On-Air"
  },
  {
    "Location": 160,
    "Name": "VJJgrandjunction,grandmesa",
    "Frequency": 147.355,
    "Duplex": "-",
    "Offset": 0.6,
    "Tone": "Tone",
    "rToneFreq": 88.5,
    "cToneFreq": 123,
    "DtcsCode": 23,
    "DtcsRxCode": 23,
    "DtcsPolarity": "NN",
    "Mode": "FM",
    "TStep": 5,
    "Comment": "CO Mesa Grand Junction, Grand Mesa KB0VJJ Colorado Connection 147.355 OPEN On-Air"
  },
  {
    "Location": 161,
    "Name": "CFIidahosprings,squawmountain",
    "Frequency": 448.675,
    "Duplex": "-",
    "Offset": 5,
    "Tone": "Tone",
    "rToneFreq": 100,
    "cToneFreq": 100,
    "DtcsCode": 23,
    "DtcsRxCode": 23,
    "DtcsPolarity": "NN",
    "Mode": "FM",
    "TStep": 5,
    "Comment": "CO Denver Idaho Springs, Squaw Mountain W0CFI W0CFI 448.675 OPEN On-Air"
  },
  {
    "Location": 162,
    "Name": "DUNidahosprings,squawmountain",
    "Frequency": 449.45,
    "Duplex": "-",
    "Offset": 5,
    "Tone": "Tone",
    "rToneFreq": 103.5,
    "cToneFreq": 127.3,
    "DtcsCode": 23,
    "DtcsRxCode": 23,
    "DtcsPolarity": "NN",
    "Mode": "FM",
    "TStep": 5,
    "Comment": "CO Clear Creek Idaho Springs, Squaw Mountain K1DUN Rocky Mountain Radio League 449.45 OPEN On-Air"
  },
  {
    "Location": 163,
    "Name": "0PCbailey,dickmountain",
    "Frequency": 146.895,
    "Duplex": "-",
    "Offset": 0.6,
    "Tone": "Tone",
    "rToneFreq": 100,
    "cToneFreq": 100,
    "DtcsCode": 23,
    "DtcsRxCode": 23,
    "DtcsPolarity": "NN",
    "Mode": "FM",
    "TStep": 5,
    "Comment": "CO Park Bailey, Dick Mountain AB0PC AB0RR 146.895 OPEN On-Air"
  },
  {
    "Location": 164,
    "Name": "G0Nidahosprings,squawmountain",
    "Frequency": 449.05,
    "Duplex": "-",
    "Offset": 5,
    "Tone": "Tone",
    "rToneFreq": 107.2,
    "cToneFreq": 107.2,
    "DtcsCode": 23,
    "DtcsRxCode": 23,
    "DtcsPolarity": "NN",
    "Mode": "FM",
    "TStep": 5,
    "Comment": "CO Denver Idaho Springs, Squaw Mountain WG0N WG0N 449.05 OPEN On-Air"
  },
  {
    "Location": 165,
    "Name": "MDPfalcon,blackforest",
    "Frequency": 447.625,
    "Duplex": "-",
    "Offset": 5,
    "Tone": "Tone",
    "rToneFreq": 100,
    "cToneFreq": 100,
    "DtcsCode": 23,
    "DtcsRxCode": 23,
    "DtcsPolarity": "NN",
    "Mode": "FM",
    "TStep": 5,
    "Comment": "CO El Paso Falcon, Black Forest KD0MDP KD0MDP The Fun Machine 447.625 OPEN On-Air"
  },
  {
    "Location": 166,
    "Name": "X0Gwoodlandpark",
    "Frequency": 146.82,
    "Duplex": "-",
    "Offset": 0.6,
    "Tone": "Tone",
    "rToneFreq": 107.2,
    "cToneFreq": 107.2,
    "DtcsCode": 23,
    "DtcsRxCode": 23,
    "DtcsPolarity": "NN",
    "Mode": "FM",
    "TStep": 5,
    "Comment": "CO Teller Woodland Park NX0G Mountain ARC 146.82 OPEN On-Air"
  },
  {
    "Location": 167,
    "Name": "X0Gwoodlandpark",
    "Frequency": 448.65,
    "Duplex": "-",
    "Offset": 5,
    "Tone": "Tone",
    "rToneFreq": 107.2,
    "cToneFreq": 107.2,
    "DtcsCode": 23,
    "DtcsRxCode": 23,
    "DtcsPolarity": "NN",
    "Mode": "FM",
    "TStep": 5,
    "Comment": "CO Teller Woodland Park NX0G Mountain ARC (MARC) MARC 448.65 OPEN On-Air"
  },
  {
    "Location": 168,
    "Name": "X0Gcoloradosprings",
    "Frequency": 447.475,
    "Duplex": "-",
    "Offset": 5,
    "Tone": "Tone",
    "rToneFreq": 107.2,
    "cToneFreq": 107.2,
    "DtcsCode": 23,
    "DtcsRxCode": 23,
    "DtcsPolarity": "NN",
    "Mode": "FM",
    "TStep": 5,
    "Comment": "CO El Paso Colorado Springs NX0G Mountain ARC (MARC) 447.475 OPEN "
  },
  {
    "Location": 169,
    "Name": "X0Glakegeorge,badgermountain",
    "Frequency": 146.685,
    "Duplex": "-",
    "Offset": 0.6,
    "Tone": "Tone",
    "rToneFreq": 107.2,
    "cToneFreq": 107.2,
    "DtcsCode": 23,
    "DtcsRxCode": 23,
    "DtcsPolarity": "NN",
    "Mode": "FM",
    "TStep": 5,
    "Comment": "CO Park Lake George, Badger Mountain NX0G Mountain ARC (MARC) 146.685 OPEN On-Air"
  },
  {
    "Location": 170,
    "Name": "X0Gcripplecreek",
    "Frequency": 147.015,
    "Duplex": "+",
    "Offset": 0.6,
    "Tone": "Tone",
    "rToneFreq": 107.2,
    "cToneFreq": 107.2,
    "DtcsCode": 23,
    "DtcsRxCode": 23,
    "DtcsPolarity": "NN",
    "Mode": "FM",
    "TStep": 5,
    "Comment": "CO Teller Cripple Creek NX0G Mountain ARC 147.015 OPEN On-Air"
  },
  {
    "Location": 171,
    "Name": "WUCwoodlandpark",
    "Frequency": 145.415,
    "Duplex": "-",
    "Offset": 0.6,
    "Tone": "Tone",
    "rToneFreq": 179.9,
    "cToneFreq": 179.9,
    "DtcsCode": 23,
    "DtcsRxCode": 23,
    "DtcsPolarity": "NN",
    "Mode": "FM",
    "TStep": 5,
    "Comment": "CO Teller Woodland Park KA0WUC MARC 145.415 OPEN "
  },
  {
    "Location": 172,
    "Name": "WUCwoodlandpark",
    "Frequency": 449.025,
    "Duplex": "-",
    "Offset": 5,
    "Tone": "Tone",
    "rToneFreq": 141.3,
    "cToneFreq": 141.3,
    "DtcsCode": 23,
    "DtcsRxCode": 23,
    "DtcsPolarity": "NN",
    "Mode": "FM",
    "TStep": 5,
    "Comment": "CO Teller Woodland Park KA0WUC Mountain Amateur Radio Club (MARC) 449.025 OPEN "
  },
  {
    "Location": 173,
    "Name": "WUCwoodlandpark",
    "Frequency": 447.675,
    "Duplex": "-",
    "Offset": 5,
    "Tone": "Tone",
    "rToneFreq": 179.9,
    "cToneFreq": 179.9,
    "DtcsCode": 23,
    "DtcsRxCode": 23,
    "DtcsPolarity": "NN",
    "Mode": "FM",
    "TStep": 5,
    "Comment": "CO Teller Woodland Park KA0WUC Mountain Amateur Radio Club (MARC) 447.675 OPEN On-Air"
  },
  {
    "Location": 174,
    "Name": "WUCwoodlandpark",
    "Frequency": 927.9,
    "Duplex": "-",
    "Offset": 25,
    "Tone": "DTCS",
    "rToneFreq": 88.5,
    "cToneFreq": 88.5,
    "DtcsCode": 205,
    "DtcsRxCode": 205,
    "DtcsPolarity": "NN",
    "Mode": "FM",
    "TStep": 5,
    "Comment": "CO Teller Woodland Park KA0WUC MARC 927.9 OPEN On-Air"
  },
  {
    "Location": 175,
    "Name": "EPSwoodlandpark,paradisepines",
    "Frequency": 449.325,
    "Duplex": "-",
    "Offset": 5,
    "Tone": "Tone",
    "rToneFreq": 103.5,
    "cToneFreq": 103.5,
    "DtcsCode": 23,
    "DtcsRxCode": 23,
    "DtcsPolarity": "NN",
    "Mode": "FM",
    "TStep": 5,
    "Comment": "CO Teller Woodland Park, Paradise Pines KA4EPS KA4EPS Amateur Radio Motorcycle Club 449.325 OPEN On-Air"
  },
  {
    "Location": 176,
    "Name": "KWDlasalle",
    "Frequency": 147,
    "Duplex": "+",
    "Offset": 0.6,
    "Tone": "Tone",
    "rToneFreq": 100,
    "cToneFreq": 100,
    "DtcsCode": 23,
    "DtcsRxCode": 23,
    "DtcsPolarity": "NN",
    "Mode": "DIG",
    "TStep": 5,
    "Comment": "CO Weld LaSalle KC0KWD Weld ARS 147 OPEN On-Air"
  },
  {
    "Location": 177,
    "Name": "KWDgreeley",
    "Frequency": 448.475,
    "Duplex": "-",
    "Offset": 5,
    "Tone": "Tone",
    "rToneFreq": 100,
    "cToneFreq": 100,
    "DtcsCode": 23,
    "DtcsRxCode": 23,
    "DtcsPolarity": "NN",
    "Mode": "FM",
    "TStep": 5,
    "Comment": "CO Weld Greeley KC0KWD Weld Amateur Radio Society (WARS) 448.475 OPEN On-Air"
  },
  {
    "Location": 178,
    "Name": "0RMrollinsville",
    "Frequency": 224.6,
    "Duplex": "-",
    "Offset": 1.6,
    "Tone": "Tone",
    "rToneFreq": 100,
    "cToneFreq": 100,
    "DtcsCode": 23,
    "DtcsRxCode": 23,
    "DtcsPolarity": "NN",
    "Mode": "FM",
    "TStep": 5,
    "Comment": "CO Gilpin Rollinsville W0RM W0RM 224.6 OPEN "
  },
  {
    "Location": 179,
    "Name": "0JZgoldhill",
    "Frequency": 146.91,
    "Duplex": "+",
    "Offset": 0.6,
    "Tone": "Tone",
    "rToneFreq": 123,
    "cToneFreq": 127.3,
    "DtcsCode": 23,
    "DtcsRxCode": 23,
    "DtcsPolarity": "NN",
    "Mode": "FM",
    "TStep": 5,
    "Comment": "CO Boulder Gold Hill W0JZ Town of Gold Hill, Colorado 146.91 OPEN On-Air"
  },
  {
    "Location": 180,
    "Name": "MOGcoloradosprings",
    "Frequency": 224.72,
    "Duplex": "-",
    "Offset": 1.6,
    "Tone": "Tone",
    "rToneFreq": 103.5,
    "cToneFreq": 103.5,
    "DtcsCode": 23,
    "DtcsRxCode": 23,
    "DtcsPolarity": "NN",
    "Mode": "FM",
    "TStep": 5,
    "Comment": "CO El Paso Colorado springs W0MOG w0mog 224.72 OPEN On-Air"
  },
  {
    "Location": 181,
    "Name": "MOGcoloradosprings",
    "Frequency": 147.39,
    "Duplex": "+",
    "Offset": 0.6,
    "Tone": "Tone",
    "rToneFreq": 103.5,
    "cToneFreq": 103.5,
    "DtcsCode": 23,
    "DtcsRxCode": 23,
    "DtcsPolarity": "NN",
    "Mode": "FM",
    "TStep": 5,
    "Comment": "CO El Paso Colorado Springs W0MOG W0MOG 147.39 OPEN On-Air"
  },
  {
    "Location": 182,
    "Name": "MOGcoloradosprings",
    "Frequency": 448.6,
    "Duplex": "-",
    "Offset": 5,
    "Tone": "Tone",
    "rToneFreq": 114.8,
    "cToneFreq": 114.8,
    "DtcsCode": 23,
    "DtcsRxCode": 23,
    "DtcsPolarity": "NN",
    "Mode": "FM",
    "TStep": 5,
    "Comment": "CO El Paso Colorado Springs W0MOG W0MOG 448.6 OPEN "
  },
  {
    "Location": 183,
    "Name": "MOGcoloradosprings",
    "Frequency": 927.8,
    "Duplex": "-",
    "Offset": 25,
    "Tone": "DTCS",
    "rToneFreq": 88.5,
    "cToneFreq": 88.5,
    "DtcsCode": 116,
    "DtcsRxCode": 116,
    "DtcsPolarity": "NN",
    "Mode": "FM",
    "TStep": 5,
    "Comment": "CO Teller Colorado Springs W0MOG 927.8 OPEN On-Air"
  },
  {
    "Location": 184,
    "Name": "0HGallenspark,afpdstation#5",
    "Frequency": 147.03,
    "Duplex": "+",
    "Offset": 0.6,
    "Tone": "Tone",
    "rToneFreq": 100,
    "cToneFreq": 100,
    "DtcsCode": 23,
    "DtcsRxCode": 23,
    "DtcsPolarity": "NN",
    "Mode": "FM",
    "TStep": 5,
    "Comment": "CO Boulder Allenspark, AFPD Station #5 KI0HG KI0HG Boulder County Amateur Radio Emergency Service 147.03 OPEN On-Air"
  },
  {
    "Location": 185,
    "Name": "LRAloveland,namaquahill",
    "Frequency": 449.575,
    "Duplex": "-",
    "Offset": 5,
    "Tone": "Tone",
    "rToneFreq": 100,
    "cToneFreq": 100,
    "DtcsCode": 23,
    "DtcsRxCode": 23,
    "DtcsPolarity": "NN",
    "Mode": "FM",
    "TStep": 5,
    "Comment": "CO Larimer Loveland, Namaqua Hill W0LRA Loveland Rptr Assoc 449.575 OPEN On-Air"
  },
  {
    "Location": 186,
    "Name": "LRAloveland,namaquahill",
    "Frequency": 147.195,
    "Duplex": "+",
    "Offset": 0.6,
    "Tone": "Tone",
    "rToneFreq": 100,
    "cToneFreq": 100,
    "DtcsCode": 23,
    "DtcsRxCode": 23,
    "DtcsPolarity": "NN",
    "Mode": "FM",
    "TStep": 5,
    "Comment": "CO Larimer Loveland, Namaqua Hill W0LRA Loveland Repeater Assoc 147.195 OPEN On-Air"
  },
  {
    "Location": 187,
    "Name": "6VVloveland",
    "Frequency": 224.32,
    "Duplex": "-",
    "Offset": 1.6,
    "Tone": "Tone",
    "rToneFreq": 100,
    "cToneFreq": 100,
    "DtcsCode": 23,
    "DtcsRxCode": 23,
    "DtcsPolarity": "NN",
    "Mode": "FM",
    "TStep": 5,
    "Comment": "CO Larimer Loveland KN6VV KN6VV 224.32 OPEN Off-Air"
  },
  {
    "Location": 188,
    "Name": "IRPcoloradosprings",
    "Frequency": 146.91,
    "Duplex": "-",
    "Offset": 0.6,
    "Tone": "Tone",
    "rToneFreq": 151.4,
    "cToneFreq": 151.4,
    "DtcsCode": 23,
    "DtcsRxCode": 23,
    "DtcsPolarity": "NN",
    "Mode": "FM",
    "TStep": 5,
    "Comment": "CO El Paso Colorado Springs K0IRP GGARC 146.91 OPEN On-Air"
  },
  {
    "Location": 189,
    "Name": "IRPcoloradosprings",
    "Frequency": 447.35,
    "Duplex": "-",
    "Offset": 5,
    "Tone": "Tone",
    "rToneFreq": 151.4,
    "cToneFreq": 151.4,
    "DtcsCode": 23,
    "DtcsRxCode": 23,
    "DtcsPolarity": "NN",
    "Mode": "FM",
    "TStep": 5,
    "Comment": "CO El Paso Colorado Springs K0IRP GGARC 447.35 OPEN On-Air"
  },
  {
    "Location": 190,
    "Name": "0TPcoloradosprings",
    "Frequency": 146.85,
    "Duplex": "-",
    "Offset": 0.6,
    "Tone": "Tone",
    "rToneFreq": 156.7,
    "cToneFreq": 103.5,
    "DtcsCode": 23,
    "DtcsRxCode": 23,
    "DtcsPolarity": "NN",
    "Mode": "FM",
    "TStep": 5,
    "Comment": "CO El Paso Colorado Springs AD0TP AD0TP Village 7 Amateur Radio Club 146.85 OPEN On-Air"
  },
  {
    "Location": 191,
    "Name": "A0Lcoloradosprings",
    "Frequency": 147.135,
    "Duplex": "+",
    "Offset": 0.6,
    "Tone": "Tone",
    "rToneFreq": 100,
    "cToneFreq": 100,
    "DtcsCode": 23,
    "DtcsRxCode": 23,
    "DtcsPolarity": "NN",
    "Mode": "FM",
    "TStep": 5,
    "Comment": "CO El Paso Colorado Springs AA0L AA0L 147.135 OPEN On-Air"
  },
  {
    "Location": 192,
    "Name": "A0Lcoloradosprings",
    "Frequency": 448.3,
    "Duplex": "-",
    "Offset": 5,
    "Tone": "Tone",
    "rToneFreq": 100,
    "cToneFreq": 100,
    "DtcsCode": 23,
    "DtcsRxCode": 23,
    "DtcsPolarity": "NN",
    "Mode": "FM",
    "TStep": 5,
    "Comment": "CO El Paso Colorado Springs AA0L AA0L 448.3 OPEN On-Air"
  },
  {
    "Location": 193,
    "Name": "SRJcoloradosprings",
    "Frequency": 224.06,
    "Duplex": "-",
    "Offset": 1.6,
    "Tone": "",
    "rToneFreq": 88.5,
    "cToneFreq": 88.5,
    "DtcsCode": 23,
    "DtcsRxCode": 23,
    "DtcsPolarity": "NN",
    "Mode": "FM",
    "TStep": 5,
    "Comment": "CO El Paso Colorado Springs KB0SRJ Pikes Peak FM Association (PPFMA) 224.06 CLOSED "
  },
  {
    "Location": 194,
    "Name": "SRJcoloradosprings,pikespeak",
    "Frequency": 146.97,
    "Duplex": "-",
    "Offset": 0.6,
    "Tone": "Tone",
    "rToneFreq": 100,
    "cToneFreq": 100,
    "DtcsCode": 23,
    "DtcsRxCode": 23,
    "DtcsPolarity": "NN",
    "Mode": "FM",
    "TStep": 5,
    "Comment": "CO El Paso Colorado Springs, Pikes Peak KB0SRJ Pikes Peak FM Assoc 146.97 OPEN On-Air"
  },
  {
    "Location": 195,
    "Name": "SRJcoloradosprings,pikespeak",
    "Frequency": 448.45,
    "Duplex": "-",
    "Offset": 5,
    "Tone": "Tone",
    "rToneFreq": 100,
    "cToneFreq": 100,
    "DtcsCode": 23,
    "DtcsRxCode": 23,
    "DtcsPolarity": "NN",
    "Mode": "FM",
    "TStep": 5,
    "Comment": "CO El Paso Colorado Springs, Pikes Peak KB0SRJ Pikes Pk FM Assoc 448.45 OPEN On-Air"
  },
  {
    "Location": 196,
    "Name": "SRJcoloradosprings,~2mieneusafanorthgate",
    "Frequency": 145.265,
    "Duplex": "-",
    "Offset": 0.6,
    "Tone": "Tone",
    "rToneFreq": 100,
    "cToneFreq": 100,
    "DtcsCode": 23,
    "DtcsRxCode": 23,
    "DtcsPolarity": "NN",
    "Mode": "DIG",
    "TStep": 5,
    "Comment": "CO El Paso Colorado Springs, ~2 mi ENE USAFA North Gate KB0SRJ Pikes Peak FM Association (http://PPFMA.ORG) 145.265 OPEN On-Air"
  },
  {
    "Location": 197,
    "Name": "SRJcoloradosprings,~2mieneusafanorthgate",
    "Frequency": 448.8,
    "Duplex": "-",
    "Offset": 5,
    "Tone": "Tone",
    "rToneFreq": 100,
    "cToneFreq": 100,
    "DtcsCode": 23,
    "DtcsRxCode": 23,
    "DtcsPolarity": "NN",
    "Mode": "FM",
    "TStep": 5,
    "Comment": "CO El Paso Colorado Springs, ~2 mi ENE USAFA North Gate KB0SRJ Pikes Peak FM Association (http://PPFMA.ORG) 448.8 OPEN On-Air"
  },
  {
    "Location": 198,
    "Name": "IFIcoloradosprings",
    "Frequency": 447.55,
    "Duplex": "-",
    "Offset": 5,
    "Tone": "Tone",
    "rToneFreq": 123,
    "cToneFreq": 123,
    "DtcsCode": 23,
    "DtcsRxCode": 23,
    "DtcsPolarity": "NN",
    "Mode": "FM",
    "TStep": 5,
    "Comment": "CO El Paso Colorado Springs WA6IFI WA6IFI 447.55 OPEN On-Air"
  },
  {
    "Location": 199,
    "Name": "IFIcoloradosprings,almagremountain",
    "Frequency": 927.725,
    "Duplex": "-",
    "Offset": 25.7,
    "Tone": "DTCS",
    "rToneFreq": 88.5,
    "cToneFreq": 88.5,
    "DtcsCode": 114,
    "DtcsRxCode": 114,
    "DtcsPolarity": "NN",
    "Mode": "P25",
    "TStep": 5,
    "Comment": "CO Teller Colorado Springs, Almagre Mountain WA6IFI WA6IFI 927.725 OPEN On-Air"
  }
]