{
  "Frequency": 449.3,
  "Offset": -5,
  "Tone": 131.8,
  "Call": "N7JJY",
  "Location": "Cheyenne, Chalk Bluffs",
  "ST/PR": "WY",
  "Use": "OPEN",
  "Mode": "FM",
  "Mi": 179.67,
  "Dir": "N",
  "": "",
  "state_id": "56",
  "ID": "34",
  "Latitude": 41.02740097,
  "Longitude": -104.78399658,
  "Downlink": 449.3,
  "Uplink": 444.3,
  "Uplink Tone": 131.8,
  "Downlink Tone": 131.8,
  "County": "Laramie",
  "Grid": "DN71OA",
  "Op Status": "On-Air",
  "Coverage": "Laramie county wy, Northern Weld and Larimer County, CO 30 mi radius.",
  "Sponsor": "N7JJY",
  "FM": "Yes; analog capable.",
  "Analog Bandwidth": 25,
  "Commands": "Keypad test -- Key down 375 then the numbers you want to test, then Key up",
  "Coordination": "WRCG",
  "Last update": "2021-02-01"
}