{
  "Frequency": 147.135,
  "Offset": 0.6,
  "Tone": 123,
  "Call": "W0SOK",
  "Location": "Cozad",
  "ST/PR": "NE",
  "Use": "OPEN",
  "Mode": "FM",
  "Mi": 129.54,
  "Dir": "E",
  "": "",
  "state_id": "31",
  "ID": "30",
  "Latitude": 40.72399902,
  "Longitude": -99.91300201,
  "Downlink": 147.135,
  "Uplink": 147.735,
  "Uplink Tone": 123,
  "County": "Dawson",
  "Grid": "EN00BR",
  "Op Status": "On-Air",
  "Sponsor": "Heartland Amateur Radio Association",
  "Features": "E-power.",
  "FM": "Yes; analog capable.",
  "Analog Bandwidth": 25,
  "Nets": "Wed 2030",
  "Last update": "2021-01-02"
}