{
  "Frequency": 927.0125,
  "Offset": -25,
  "Tone": 88.5,
  "Call": "NC9RS",
  "Location": "Ridgecrest",
  "ST/PR": "CA",
  "Use": "OPEN",
  "Mode": "FM EchoLink",
  "Mi": 146.63,
  "Dir": "WSW",
  "": "Node Offline",
  "state_id": "06",
  "ID": "14005",
  "Latitude": 35.62250137,
  "Longitude": -117.67099762,
  "Downlink": 927.0125,
  "Uplink": 902.0125,
  "Uplink Tone": 88.5,
  "County": "Kern",
  "Op Status": "On-Air",
  "FM": "Yes; analog capable.",
  "Analog Bandwidth": "",
  "EchoLink": 487039,
  "Coordination": "NARCC",
  "Last update": "2017-06-23"
}