{
  "Frequency": 51.92,
  "Offset": -0.5,
  "Tone": 82.5,
  "Call": "WA6MDJ",
  "Location": "Indio, Indio Hills",
  "ST/PR": "CA",
  "Use": "OPEN",
  "Mode": "FM",
  "Mi": 168.31,
  "Dir": "SSW",
  "": "",
  "state_id": "06",
  "ID": "30",
  "Latitude": 33.89419937,
  "Longitude": -116.2009964,
  "Downlink": 51.92,
  "Uplink": 51.42,
  "Uplink Tone": 82.5,
  "County": "Riverside",
  "On-air": "Unknown",
  "Sponsor": "Baldwin Hills ARC",
  "FM": "Yes; analog capable.",
  "Analog Bandwidth": "",
  "Last update": "2016-10-24"
}