{
  "Frequency": 223.88,
  "Offset": -1.6,
  "Tone": 110.9,
  "Call": "WA6HYQ",
  "Location": "La Quinta, Santa Rosa Mountain",
  "ST/PR": "CA",
  "Use": "OPEN",
  "Mode": "FM",
  "Mi": 196.39,
  "Dir": "SSW",
  "": "",
  "state_id": "06",
  "ID": "807",
  "Latitude": 33.54510117,
  "Longitude": -116.46900177,
  "Downlink": 223.88,
  "Uplink": 222.28,
  "Uplink Tone": 110.9,
  "Downlink Tone": 110.9,
  "County": "Riverside",
  "Grid": "DM13sn",
  "Op Status": "On-Air",
  "Coverage": "Wide area.",
  "FM": "Yes; analog capable.",
  "Analog Bandwidth": "",
  "Links": "Full-time to 445.02000 (W6CDF) at Cactus City, CA . Full-time to 146.67000 (WA6HYQ) at Moreno Valley, Civic Center, CA .",
  "Coordination": 220,
  "Last update": "2019-11-21"
}