{
  "Frequency": 448.18,
  "Offset": -5,
  "Tone": "",
  "Call": "WB6TZU",
  "Location": "Lake Arrowhead, Heaps Peak",
  "ST/PR": "CA",
  "Use": "PRIVATE",
  "Mode": "FM",
  "Mi": 187.21,
  "Dir": "SW",
  "": "",
  "state_id": "06",
  "ID": "9482",
  "Latitude": 34.10829926,
  "Longitude": -117.29000092,
  "Downlink": 448.18,
  "Uplink": 443.18,
  "County": "San Bernardino",
  "Op Status": "On-Air",
  "Sponsor": "Skyline ARC",
  "FM": "Yes; analog capable.",
  "Analog Bandwidth": "",
  "Coordination": "SCRRBA",
  "Last update": "2013-04-20"
}