{
  "Frequency": 146.82,
  "Offset": -0.6,
  "Tone": 107.2,
  "Call": "W0GJT",
  "Location": "Grand Junction, 9 Mile, Hwy 141, Unaweep",
  "ST/PR": "CO",
  "Use": "OPEN",
  "VOIP": "A",
  "DGTL": "",
  "Mi": 184.11,
  "Dir": "WNW",
  "": "",
  "state_id": "08",
  "ID": "261",
  "Latitude": 39.06389999,
  "Longitude": -108.55000305,
  "Downlink": 146.82,
  "Uplink": 146.22,
  "Uplink Tone": 107.2,
  "County": "Mesa",
  "Op Status": "On-Air",
  "Coverage": "Wide area: North Western Colorado - South to Montrose and East on I-70.",
  "FM": "Yes; analog capable.",
  "Analog Bandwidth": "",
  "AllStar": 43554,
  "Commands": "Enter *83 node# to link. *81 Unlink",
  "Coordination": "CCARC",
  "Last update": "2019-02-12"
}