{
  "Frequency": 446.8375,
  "Offset": -5,
  "Tone": "CC",
  "Call": "WA2YZT",
  "Location": "Golden, Lookout",
  "ST/PR": "CO",
  "Use": "OPEN",
  "VOIP": "",
  "DGTL": "D",
  "Mi": 158.19,
  "Dir": "E",
  "": "",
  "state_id": "08",
  "ID": "3753",
  "Latitude": 39.73049927,
  "Longitude": -105.23200226,
  "Downlink": 446.8375,
  "Uplink": 441.8375,
  "DMR Enabled": true,
  "Color Code": 7,
  "DMR ID": 310802,
  "IPSC Network": "RMHR c Record retrieved from radioid.net",
  "Wide Network": "",
  "County": "Jefferson",
  "Grid": "DM79JR",
  "Op Status": "On-Air",
  "Sponsor": "WA2YZT",
  "Features": 200,
  "Links": "Full-time to the Colorado TRBO System .",
  "Notes": "See website for more info on CC/TS/TG programming. www.rmham.org",
  "Coordination": "CCARC",
  "Last update": "2019-11-27"
}