{
  "Frequency": 147.27,
  "Offset": 0.6,
  "Tone": "",
  "Call": "",
  "Location": "Colorado Springs",
  "ST/PR": "CO",
  "Use": "OPEN",
  "VOIP": "",
  "DGTL": "",
  "Mi": 34.59,
  "Dir": "NE",
  "": "",
  "state_id": "08",
  "ID": "46",
  "Latitude": 38.83810043,
  "Longitude": -104.82099915,
  "Downlink": 147.27,
  "Uplink": 147.87,
  "County": "El Paso",
  "Op Status": "On-Air",
  "Sponsor": "TRA",
  "Features": "E-power.",
  "FM": "Yes; analog capable.",
  "Analog Bandwidth": "",
  "Last update": "2016-08-10"
}