{
  "Frequency": 147.12,
  "Offset": 0.6,
  "Tone": 88.5,
  "Call": "N0ARA",
  "Location": "Critchell, Critchell Mountain",
  "ST/PR": "CO",
  "Use": "OPEN",
  "VOIP": "",
  "DGTL": "",
  "Mi": 73.94,
  "Dir": "N",
  "": "",
  "state_id": "08",
  "ID": "59",
  "Latitude": 39.51480103,
  "Longitude": -105.35299683,
  "Downlink": 147.12,
  "Uplink": 147.72,
  "Uplink Tone": 88.5,
  "Downlink Tone": 88.5,
  "County": "Jefferson",
  "Grid": "DM79HM",
  "Op Status": "On-Air",
  "Coverage": "Denver metro and east.",
  "Sponsor": "Aurora Repeater Association",
  "Features": "E-power.",
  "Web links": "http://www.n0ara.org",
  "Coordination": "CCARC",
  "Last update": "2016-01-17"
}