{
  "Frequency": 447.4,
  "Offset": -5,
  "Tone": 67,
  "Call": "WB0WDF",
  "Location": "Cripple Creek",
  "ST/PR": "CO",
  "Use": "OPEN",
  "VOIP": "",
  "DGTL": "",
  "Mi": 138.11,
  "Dir": "ESE",
  "": "",
  "state_id": "08",
  "ID": "66",
  "Latitude": 38.74670029,
  "Longitude": -105.1780014,
  "Downlink": 447.4,
  "Uplink": 442.4,
  "Uplink Tone": 67,
  "County": "Teller",
  "Op Status": "On-Air",
  "Sponsor": "WB0WDF",
  "Features": "E-power, Solar, Remote Base",
  "Coordination": "CCARC",
  "Last update": "2012-06-15"
}