{
  "Frequency": 147.135,
  "Offset": 0.6,
  "Tone": 100,
  "Call": "AA0L",
  "Location": "Colorado Springs",
  "ST/PR": "CO",
  "Use": "OPEN",
  "VOIP": "",
  "DGTL": "",
  "Mi": 55.82,
  "Dir": "S",
  "": "",
  "state_id": "08",
  "ID": "8176",
  "Latitude": 38.83969879,
  "Longitude": -104.80000305,
  "Downlink": 147.135,
  "Uplink": 147.735,
  "Uplink Tone": 100,
  "County": "El Paso",
  "Grid": "DM78OU",
  "Op Status": "On-Air",
  "Sponsor": "AA0L",
  "Features": 6,
  "Coordination": "CCARC",
  "Last update": "2016-04-08"
}