{
  "Frequency": 447.975,
  "Offset": -5,
  "Tone": 82.5,
  "Call": "W7HTL",
  "Location": "Las Vegas, Blue Diamond Hill",
  "ST/PR": "NV",
  "Use": "OPEN",
  "Mode": "FM",
  "Mi": 14.92,
  "Dir": "WSW",
  "": "",
  "state_id": "32",
  "ID": "9514",
  "Latitude": 36.10250092,
  "Longitude": -115.39399719,
  "Downlink": 447.975,
  "Uplink": 442.975,
  "Uplink Tone": 82.5,
  "Downlink Tone": 82.5,
  "County": "Clark",
  "Grid": "DM26HC",
  "Op Status": "On-Air",
  "Sponsor": "Nevada Amateur Radio Rptrs Inc",
  "Features": "Remote base, e-power (solar).",
  "FM": "Yes; analog capable.",
  "Analog Bandwidth": "",
  "Nets": "Sat at 09:00. Mon at 20:30.",
  "Coordination": "SNRC",
  "Last update": "2018-07-01"
}