{
  "Frequency": 449.55,
  "Offset": -5,
  "Tone": 100,
  "Call": "WA7GIE",
  "Location": "Coalville, Lewis Peak",
  "ST/PR": "UT",
  "Use": "OPEN",
  "Mode": "FM",
  "Mi": 188.08,
  "Dir": "NNW",
  "": "",
  "state_id": "49",
  "ID": "234",
  "Latitude": 40.85499954,
  "Longitude": -111.48000336,
  "Downlink": 449.55,
  "Uplink": 444.55,
  "Uplink Tone": 100,
  "County": "Summit",
  "Grid": "DN40GU",
  "Op Status": "On-Air",
  "Coverage": "Wide area: Park City, Heber, Coalville and other nearby communities. Western side of the Salt Lake valley.",
  "Features": "IRLP",
  "FM": "Yes; analog capable.",
  "Analog Bandwidth": "",
  "Notes": "PL 131.8? Node usually connected to 5620 .",
  "Coordination": "UVHFS",
  "Last update": "2012-11-27"
}