{
  "Frequency": 145.31,
  "Offset": -0.6,
  "Tone": 103.5,
  "Call": "WA7KMF",
  "Location": "Red Spur",
  "ST/PR": "UT",
  "Use": "OPEN",
  "Mode": "FM",
  "Mi": 139.04,
  "Dir": "E",
  "": "",
  "state_id": "49",
  "ID": "241",
  "Latitude": 41.6371994,
  "Longitude": -111.41600037,
  "Downlink": 145.31,
  "Uplink": 144.71,
  "Uplink Tone": 103.5,
  "County": "Cache",
  "Grid": "DN41HP",
  "Op Status": "On-Air",
  "Coverage": "Wide area: Logan and immediately surrounding communities.",
  "Sponsor": "Bridgerland ARC",
  "Features": "Autopatch, 5,700'.",
  "FM": "Yes; analog capable.",
  "Analog Bandwidth": "",
  "Links": "Full-time to 146.72000 (WA7KMF) at Logan, Mt Logan, UT .",
  "Web links": "BARC Repeaters",
  "Coordination": "UVHFS",
  "Last update": "2016-12-13"
}