{
  "Frequency": 146.61,
  "Offset": -0.6,
  "Tone": 88.5,
  "Call": "K7SDC",
  "Location": "Monticello, Abajo Peak",
  "ST/PR": "UT",
  "Use": "OPEN",
  "Mode": "FM EchoLink IRLP",
  "Mi": 194.11,
  "Dir": "WSW",
  "": "ON - IDLE",
  "state_id": "49",
  "ID": "60",
  "Latitude": 37.83919907,
  "Longitude": -109.46199799,
  "Downlink": 146.61,
  "Uplink": 146.01,
  "Uplink Tone": 88.5,
  "County": "San Juan",
  "Grid": "DM57GU",
  "Op Status": "On-Air",
  "Coverage": "Wide area: Southeastern Utah, Southwest Colorado, Northwest New Mexico and extreme Northeastern Arizona, including Monticello, Blanding, and much of Canyonlands National Park. 100 mi radius.",
  "Sponsor": "Sinbad Desert ARC",
  "Features": "Remote base.",
  "FM": "Yes; analog capable.",
  "Analog Bandwidth": "",
  "Links": "Full-time to the Sinbad Desert (SDARC) System .",
  "EchoLink": 64264,
  "IRLP": 3270,
  "Notes": 11.36,
  "Web links": "http://www.sdarc.us/repeaters/abajo.html",
  "Coordination": "UVHFS",
  "Last update": "2020-12-27"
}