{
  "Frequency": 448.35,
  "Offset": -5,
  "Tone": "",
  "Call": "KC7OXI",
  "Location": "Draper, South Mountain",
  "ST/PR": "UT",
  "Use": "OPEN",
  "Mode": "FM",
  "Mi": 104.16,
  "Dir": "SE",
  "": "",
  "state_id": "49",
  "ID": "93",
  "Latitude": 40.46390152,
  "Longitude": -111.89299774,
  "Downlink": 448.35,
  "Uplink": 443.35,
  "County": "Salt Lake",
  "Grid": "DN40BL",
  "Op Status": "On-Air",
  "Coverage": "Utah County from Alpine to Payson. Salt Lake Valley communities from Salt Lake City to Draper.",
  "Sponsor": "Rocky Mtn RA",
  "Features": 5,
  "FM": "Yes; analog capable.",
  "Analog Bandwidth": "",
  "Coordination": "UVHFS",
  "Last update": "2015-07-19"
}